Workbook
Name j: scon!#REF!
Name j: pcon!#REF!

Sheet pcon
A1: MASTER CONTRACT - PURCHASE
A3: Sl.no | B3: Vendor Name | C3: Vendor ID | D3: Contract ID | E3: Period | G3: Base price (per kg) | H3: Quantity (kgs) | I3: Breach Logic | L3: Renewal Reference
E4: Start | F4: End | H4: Agreed Qty | I4: Breach Responsibility | J4: Penalty / Discount (%) | K4: Remedy Days | M4: Ignore Remaining Qty
A5: 1 | B5: Samurai Traders | C5: 675597 | D5: 675597-R0 | E5: 46182 | F5: 46203 | G5: 150 | H5: 100000 | I5: Pending | J5: 10 | K5: 15 | M5: 0
A6: 2 | B6: Pala Traders | C6: 893281 | D6: 893281-R0 | E6: 46113 | F6: 46234 | G6: 135 | H6: 200000 | I6: Pending | J6: 0 | K6: 0
A7: 3 | B7: Samwell Suppliers | C7: 328422 | D7: 328422-R0 | E7: 46175 | F7: 46234 | G7: 140 | H7: 100000 | I7: Pending | J7: 0 | K7: 0 | M7: 0
A8: 4 | B8: Sukumaran Co | C8: 563124 | D8: 563124-R0 | E8: 46174 | F8: 46192 | G8: 111 | H8: 100000 | I8: Pending | J8: 0 | K8: 0 | M8: 0
A9: 5 | B9: Ganga Neha Traders | C9: 128432 | D9: 128432-R0 | E9: 46118 | F9: 46173 | G9: 137 | H9: 300000 | I9: Pending | J9: 0 | K9: 0 | M9: 1
A10: 6 | B10: Ganga Neha Traders | C10: 128432 | D10: 128432-R1 | E10: 46180 | F10: 46183 | G10: 137 | H10: 300000 | I10: Pending | J10: 0 | K10: 0 | L10: 128432-R0 | M10: 0
A11: 7
A12: 8
A13: 9
A14: 10
A15: 11
A16: 12
A17: 13
A18: 14
A19: 15
A20: 16
A21: 17
A22: 18
... A2004: 2000

Sheet scon
A1: MASTER CONTRACT - SALES
A3: Sl.no | B3: Customer Name | C3: Customer ID | D3: Contract ID | E3: Period | G3: Base price (per kg) | H3: Quantity (kgs) | I3: Breach Logic | L3: Renewal Reference
E4: Start | F4: End | H4: Agreed Qty | I4: Breach Responsibility | J4: Penalty / Discount (%) | K4: Remedy Days | M4: Ignore Remaining Qty
A5: 1
A6: 2
A7: 3
A8: 4
A9: 5
A10: 6
A11: 7
A12: 8
A13: 9
A14: 10
A15: 11
A16: 12
... A2004: 2000

Sheet purchase
A1: PURCHASE SHEET
A3: Sl no. | B3: Vendor ID | C3: Contract ID | D3: Invoice Number | E3: Date | G3: Weight (kgs) | L3: GST (%) | M3: TDS 194Q (%) | N3: Unloading Charge
E4: Purchase Order | F4: Delivery | G4: Invoice Weight | H4: Before Unloading | I4: Carrier weight | J4: No: of Bags (1kg per bag) | K4: Calculated DRC (%)
A5: 1 | B5: 328422 | C5: 328422-R0 | D5: ABC12345678 | E5: 46175 | F5: 46176 | G5: 1e+23 | H5: 20000 | I5: 3500 | J5: 200 | K5: 77 | L5: 5 | M5: 10 | N5: 2000
A6: 2 | B6: 563124 | C6: 563124-R0 | D6: AH37BDB8236B | E6: 46182 | F6: 46202 | G6: 5000 | H6: 10000 | I6: 3000 | J6: 200 | K6: 69.9 | L6: 5 | M6: 10 | N6: 0
A7: 3 | B7: 563124 | C7: 563124-R0 | D7: HDGJY2367B | E7: 46176 | G7: 0 | H7: 10000 | I7: 3000 | J7: 0 | K7: 80 | L7: 5 | M7: 0.1 | N7: 0
A8: 4
A9: 5
A10: 6
A11: 7
A12: 8
A13: 9
A14: 10
A15: 11
A16: 12
A17: 13
A18: 14
A19: 15
... A2504: 2500

Sheet sales
A1: SALES SHEET
A3: Sl no. | B3: Customer ID | C3: Contract ID | D3: Invoice Number | E3: Date | G3: Weight | H3: Rates (%) | J3: Loading Charge
E4: Sales Order | F4: Dispatch | H4: GST | I4: TCS 194Q
A5: 1
A6: 2
A7: 3
A8: 4
A9: 5
A10: 6
A11: 7
A12: 8
A13: 9
A14: 10
A15: 11
A16: 12
... A2504: 2500

Sheet production
A1: MASTER PRODUCTION SHEET
A3: Sl no. | B3: Batch ID | C3: Production Date | D3: Supplier Name | E3: Supplier ID | F3: Invoice Number | G3: Item | K3: Weight (kgs) | P3: DRC (%)
G4: Raw Material | H4: Code | I4: Product | J4: Code | K4: Quantity Available | L4: Input | M4: Output | N4: Remaining Quantity | O4: Production Loss | P4: Initial (Test) | Q4: Actual | R4: DRC Variance
A5: 1 | B5: =IF(OR(C5="",F5=""),"", "PRD-" & TEXT(DAY(C5),"00") & CHOOSE(MONTH(C5),"A","B","C","D","E","F","G","H","I","J","K","L") & TEXT(YEAR(C5),"00") & "-" & RIGHT(F5,4)) | D5: =IF(F5="","",_xlfn.XLOOKUP(F5,purchase!D:D,purchase!#REF!,"")) | E5: =IF(F5="","",_xlfn.XLOOKUP(F5,purchase!D:D,purchase!B:B,"")) | G5: =IF(H5="NRFC","Natural Rubber Field Coagulam","") | H5: =IF(F5="","",_xlfn.XLOOKUP(F5,purchase!D:D,purchase!#REF!,"")) | I5: =IF(J5="ISNR20","Natural Rubber-TSNR (ISNR-20)","") | J5: =IF(H5="NRFC","ISNR20","") | K5: =_xlfn.SINGLE(IF(F5="","",_xlfn.XLOOKUP(F5,purchase!D:D,purchase!#REF!,""))) | N5: =IF(F5="","", MAX(0, _xlfn.XLOOKUP(F5,purchase!D:D,purchase!#REF!,"") - SUMIFS(L:L,F:F,F5))) | O5: =IF(OR(L5="",M5=""),"",L5-M5) | P5: =_xlfn.SINGLE(IF(F5="","",_xlfn.XLOOKUP(F5,purchase!D:D,purchase!K:K,""))) | Q5: =IF(OR(L5="",M5=""),"",M5/L5) | R5: =IF(OR(P5="",Q5=""),"",Q5-P5)
A6: 2 | B6: =IF(OR(C6="",F6=""),"", "PRD-" & TEXT(DAY(C6),"00") & CHOOSE(MONTH(C6),"A","B","C","D","E","F","G","H","I","J","K","L") & TEXT(YEAR(C6),"00") & "-" & RIGHT(F6,4)) | D6: =IF(F6="","",_xlfn.XLOOKUP(F6,purchase!D:D,purchase!#REF!,"")) | E6: =IF(F6="","",_xlfn.XLOOKUP(F6,purchase!D:D,purchase!B:B,"")) | G6: =IF(H6="NRFC","Natural Rubber Field Coagulam","") | H6: =IF(F6="","",_xlfn.XLOOKUP(F6,purchase!D:D,purchase!#REF!,"")) | I6: =IF(J6="ISNR20","Natural Rubber-TSNR (ISNR-20)","") | J6: =IF(H6="NRFC","ISNR20","") | K6: =_xlfn.SINGLE(IF(F6="","",_xlfn.XLOOKUP(F6,purchase!D:D,purchase!#REF!,""))) | N6: =IF(F6="","", MAX(0, _xlfn.XLOOKUP(F6,purchase!D:D,purchase!#REF!,"") - SUMIFS(L:L,F:F,F6))) | O6: =IF(OR(L6="",M6=""),"",L6-M6) | P6: =_xlfn.SINGLE(IF(F6="","",_xlfn.XLOOKUP(F6,purchase!D:D,purchase!K:K,""))) | Q6: =IF(OR(L6="",M6=""),"",M6/L6) | R6: =IF(OR(P6="",Q6=""),"",Q6-P6)
A7: 3 | B7: =IF(OR(C7="",F7=""),"", "PRD-" & TEXT(DAY(C7),"00") & CHOOSE(MONTH(C7),"A","B","C","D","E","F","G","H","I","J","K","L") & TEXT(YEAR(C7),"00") & "-" & RIGHT(F7,4)) | D7: =IF(F7="","",_xlfn.XLOOKUP(F7,purchase!D:D,purchase!#REF!,"")) | E7: =IF(F7="","",_xlfn.XLOOKUP(F7,purchase!D:D,purchase!B:B,"")) | G7: =IF(H7="NRFC","Natural Rubber Field Coagulam","") | H7: =IF(F7="","",_xlfn.XLOOKUP(F7,purchase!D:D,purchase!#REF!,"")) | I7: =IF(J7="ISNR20","Natural Rubber-TSNR (ISNR-20)","") | J7: =IF(H7="NRFC","ISNR20","") | K7: =_xlfn.SINGLE(IF(F7="","",_xlfn.XLOOKUP(F7,purchase!D:D,purchase!#REF!,""))) | N7: =IF(F7="","", MAX(0, _xlfn.XLOOKUP(F7,purchase!D:D,purchase!#REF!,"") - SUMIFS(L:L,F:F,F7))) | O7: =IF(OR(L7="",M7=""),"",L7-M7) | P7: =_xlfn.SINGLE(IF(F7="","",_xlfn.XLOOKUP(F7,purchase!D:D,purchase!K:K,""))) | Q7: =IF(OR(L7="",M7=""),"",M7/L7) | R7: =IF(OR(P7="",Q7=""),"",Q7-P7)
A8: 4 | B8: =IF(OR(C8="",F8=""),"", "PRD-" & TEXT(DAY(C8),"00") & CHOOSE(MONTH(C8),"A","B","C","D","E","F","G","H","I","J","K","L") & TEXT(YEAR(C8),"00") & "-" & RIGHT(F8,4)) | D8: =IF(F8="","",_xlfn.XLOOKUP(F8,purchase!D:D,purchase!#REF!,"")) | E8: =IF(F8="","",_xlfn.XLOOKUP(F8,purchase!D:D,purchase!B:B,"")) | G8: =IF(H8="NRFC","Natural Rubber Field Coagulam","") | H8: =IF(F8="","",_xlfn.XLOOKUP(F8,purchase!D:D,purchase!#REF!,"")) | I8: =IF(J8="ISNR20","Natural Rubber-TSNR (ISNR-20)","") | J8: =IF(H8="NRFC","ISNR20","") | K8: =_xlfn.SINGLE(IF(F8="","",_xlfn.XLOOKUP(F8,purchase!D:D,purchase!#REF!,""))) | N8: =IF(F8="","", MAX(0, _xlfn.XLOOKUP(F8,purchase!D:D,purchase!#REF!,"") - SUMIFS(L:L,F:F,F8))) | O8: =IF(OR(L8="",M8=""),"",L8-M8) | P8: =_xlfn.SINGLE(IF(F8="","",_xlfn.XLOOKUP(F8,purchase!D:D,purchase!K:K,""))) | Q8: =IF(OR(L8="",M8=""),"",M8/L8) | R8: =IF(OR(P8="",Q8=""),"",Q8-P8)
A9: 5 | B9: =IF(OR(C9="",F9=""),"", "PRD-" & TEXT(DAY(C9),"00") & CHOOSE(MONTH(C9),"A","B","C","D","E","F","G","H","I","J","K","L") & TEXT(YEAR(C9),"00") & "-" & RIGHT(F9,4)) | D9: =IF(F9="","",_xlfn.XLOOKUP(F9,purchase!D:D,purchase!#REF!,"")) | E9: =IF(F9="","",_xlfn.XLOOKUP(F9,purchase!D:D,purchase!B:B,"")) | G9: =IF(H9="NRFC","Natural Rubber Field Coagulam","") | H9: =IF(F9="","",_xlfn.XLOOKUP(F9,purchase!D:D,purchase!#REF!,"")) | I9: =IF(J9="ISNR20","Natural Rubber-TSNR (ISNR-20)","") | J9: =IF(H9="NRFC","ISNR20","") | K9: =_xlfn.SINGLE(IF(F9="","",_xlfn.XLOOKUP(F9,purchase!D:D,purchase!#REF!,""))) | N9: =IF(F9="","", MAX(0, _xlfn.XLOOKUP(F9,purchase!D:D,purchase!#REF!,"") - SUMIFS(L:L,F:F,F9))) | O9: =IF(OR(L9="",M9=""),"",L9-M9) | P9: =_xlfn.SINGLE(IF(F9="","",_xlfn.XLOOKUP(F9,purchase!D:D,purchase!K:K,""))) | Q9: =IF(OR(L9="",M9=""),"",M9/L9) | R9: =IF(OR(P9="",Q9=""),"",Q9-P9)
A10: 6 | B10: =IF(OR(C10="",F10=""),"", "PRD-" & TEXT(DAY(C10),"00") & CHOOSE(MONTH(C10),"A","B","C","D","E","F","G","H","I","J","K","L") & TEXT(YEAR(C10),"00") & "-" & RIGHT(F10,4)) | D10: =IF(F10="","",_xlfn.XLOOKUP(F10,purchase!D:D,purchase!#REF!,"")) | E10: =IF(F10="","",_xlfn.XLOOKUP(F10,purchase!D:D,purchase!B:B,"")) | G10: =IF(H10="NRFC","Natural Rubber Field Coagulam","") | H10: =IF(F10="","",_xlfn.XLOOKUP(F10,purchase!D:D,purchase!#REF!,"")) | I10: =IF(J10="ISNR20","Natural Rubber-TSNR (ISNR-20)","") | J10: =IF(H10="NRFC","ISNR20","") | K10: =_xlfn.SINGLE(IF(F10="","",_xlfn.XLOOKUP(F10,purchase!D:D,purchase!#REF!,""))) | N10: =IF(F10="","", MAX(0, _xlfn.XLOOKUP(F10,purchase!D:D,purchase!#REF!,"") - SUMIFS(L:L,F:F,F10))) | O10: =IF(OR(L10="",M10=""),"",L10-M10) | P10: =_xlfn.SINGLE(IF(F10="","",_xlfn.XLOOKUP(F10,purchase!D:D,purchase!K:K,""))) | Q10: =IF(OR(L10="",M10=""),"",M10/L10) | R10: =IF(OR(P10="",Q10=""),"",Q10-P10)
A11: 7 | B11: =IF(OR(C11="",F11=""),"", "PRD-" & TEXT(DAY(C11),"00") & CHOOSE(MONTH(C11),"A","B","C","D","E","F","G","H","I","J","K","L") & TEXT(YEAR(C11),"00") & "-" & RIGHT(F11,4)) | D11: =IF(F11="","",_xlfn.XLOOKUP(F11,purchase!D:D,purchase!#REF!,"")) | E11: =IF(F11="","",_xlfn.XLOOKUP(F11,purchase!D:D,purchase!B:B,"")) | G11: =IF(H11="NRFC","Natural Rubber Field Coagulam","") | H11: =IF(F11="","",_xlfn.XLOOKUP(F11,purchase!D:D,purchase!#REF!,"")) | I11: =IF(J11="ISNR20","Natural Rubber-TSNR (ISNR-20)","") | J11: =IF(H11="NRFC","ISNR20","") | K11: =_xlfn.SINGLE(IF(F11="","",_xlfn.XLOOKUP(F11,purchase!D:D,purchase!#REF!,""))) | N11: =IF(F11="","", MAX(0, _xlfn.XLOOKUP(F11,purchase!D:D,purchase!#REF!,"") - SUMIFS(L:L,F:F,F11))) | O11: =IF(OR(L11="",M11=""),"",L11-M11) | P11: =_xlfn.SINGLE(IF(F11="","",_xlfn.XLOOKUP(F11,purchase!D:D,purchase!K:K,""))) | Q11: =IF(OR(L11="",M11=""),"",M11/L11) | R11: =IF(OR(P11="",Q11=""),"",Q11-P11)
A12: 8 | B12: =IF(OR(C12="",F12=""),"", "PRD-" & TEXT(DAY(C12),"00") & CHOOSE(MONTH(C12),"A","B","C","D","E","F","G","H","I","J","K","L") & TEXT(YEAR(C12),"00") & "-" & RIGHT(F12,4)) | D12: =IF(F12="","",_xlfn.XLOOKUP(F12,purchase!D:D,purchase!#REF!,"")) | E12: =IF(F12="","",_xlfn.XLOOKUP(F12,purchase!D:D,purchase!B:B,"")) | G12: =IF(H12="NRFC","Natural Rubber Field Coagulam","") | H12: =IF(F12="","",_xlfn.XLOOKUP(F12,purchase!D:D,purchase!#REF!,"")) | I12: =IF(J12="ISNR20","Natural Rubber-TSNR (ISNR-20)","") | J12: =IF(H12="NRFC","ISNR20","") | K12: =_xlfn.SINGLE(IF(F12="","",_xlfn.XLOOKUP(F12,purchase!D:D,purchase!#REF!,""))) | N12: =IF(F12="","", MAX(0, _xlfn.XLOOKUP(F12,purchase!D:D,purchase!#REF!,"") - SUMIFS(L:L,F:F,F12))) | O12: =IF(OR(L12="",M12=""),"",L12-M12) | P12: =_xlfn.SINGLE(IF(F12="","",_xlfn.XLOOKUP(F12,purchase!D:D,purchase!K:K,""))) | Q12: =IF(OR(L12="",M12=""),"",M12/L12) | R12: =IF(OR(P12="",Q12=""),"",Q12-P12)
A13: 9 | B13: =IF(OR(C13="",F13=""),"", "PRD-" & TEXT(DAY(C13),"00") & CHOOSE(MONTH(C13),"A","B","C","D","E","F","G","H","I","J","K","L") & TEXT(YEAR(C13),"00") & "-" & RIGHT(F13,4)) | D13: =IF(F13="","",_xlfn.XLOOKUP(F13,purchase!D:D,purchase!#REF!,"")) | E13: =IF(F13="","",_xlfn.XLOOKUP(F13,purchase!D:D,purchase!B:B,"")) | G13: =IF(H13="NRFC","Natural Rubber Field Coagulam","") | H13: =IF(F13="","",_xlfn.XLOOKUP(F13,purchase!D:D,purchase!#REF!,"")) | I13: =IF(J13="ISNR20","Natural Rubber-TSNR (ISNR-20)","") | J13: =IF(H13="NRFC","ISNR20","") | K13: =_xlfn.SINGLE(IF(F13="","",_xlfn.XLOOKUP(F13,purchase!D:D,purchase!#REF!,""))) | N13: =IF(F13="","", MAX(0, _xlfn.XLOOKUP(F13,purchase!D:D,purchase!#REF!,"") - SUMIFS(L:L,F:F,F13))) | O13: =IF(OR(L13="",M13=""),"",L13-M13) | P13: =_xlfn.SINGLE(IF(F13="","",_xlfn.XLOOKUP(F13,purchase!D:D,purchase!K:K,""))) | Q13: =IF(OR(L13="",M13=""),"",M13/L13) | R13: =IF(OR(P13="",Q13=""),"",Q13-P13)
A14: 10 | B14: =IF(OR(C14="",F14=""),"", "PRD-" & TEXT(DAY(C14),"00") & CHOOSE(MONTH(C14),"A","B","C","D","E","F","G","H","I","J","K","L") & TEXT(YEAR(C14),"00") & "-" & RIGHT(F14,4)) | D14: =IF(F14="","",_xlfn.XLOOKUP(F14,purchase!D:D,purchase!#REF!,"")) | E14: =IF(F14="","",_xlfn.XLOOKUP(F14,purchase!D:D,purchase!B:B,"")) | G14: =IF(H14="NRFC","Natural Rubber Field Coagulam","") | H14: =IF(F14="","",_xlfn.XLOOKUP(F14,purchase!D:D,purchase!#REF!,"")) | I14: =IF(J14="ISNR20","Natural Rubber-TSNR (ISNR-20)","") | J14: =IF(H14="NRFC","ISNR20","") | K14: =_xlfn.SINGLE(IF(F14="","",_xlfn.XLOOKUP(F14,purchase!D:D,purchase!#REF!,""))) | N14: =IF(F14="","", MAX(0, _xlfn.XLOOKUP(F14,purchase!D:D,purchase!#REF!,"") - SUMIFS(L:L,F:F,F14))) | O14: =IF(OR(L14="",M14=""),"",L14-M14) | P14: =_xlfn.SINGLE(IF(F14="","",_xlfn.XLOOKUP(F14,purchase!D:D,purchase!K:K,""))) | Q14: =IF(OR(L14="",M14=""),"",M14/L14) | R14: =IF(OR(P14="",Q14=""),"",Q14-P14)
A15: 11 | B15: =IF(OR(C15="",F15=""),"", "PRD-" & TEXT(DAY(C15),"00") & CHOOSE(MONTH(C15),"A","B","C","D","E","F","G","H","I","J","K","L") & TEXT(YEAR(C15),"00") & "-" & RIGHT(F15,4)) | D15: =IF(F15="","",_xlfn.XLOOKUP(F15,purchase!D:D,purchase!#REF!,"")) | E15: =IF(F15="","",_xlfn.XLOOKUP(F15,purchase!D:D,purchase!B:B,"")) | G15: =IF(H15="NRFC","Natural Rubber Field Coagulam","") | H15: =IF(F15="","",_xlfn.XLOOKUP(F15,purchase!D:D,purchase!#REF!,"")) | I15: =IF(J15="ISNR20","Natural Rubber-TSNR (ISNR-20)","") | J15: =IF(H15="NRFC","ISNR20","") | K15: =_xlfn.SINGLE(IF(F15="","",_xlfn.XLOOKUP(F15,purchase!D:D,purchase!#REF!,""))) | N15: =IF(F15="","", MAX(0, _xlfn.XLOOKUP(F15,purchase!D:D,purchase!#REF!,"") - SUMIFS(L:L,F:F,F15))) | O15: =IF(OR(L15="",M15=""),"",L15-M15) | P15: =_xlfn.SINGLE(IF(F15="","",_xlfn.XLOOKUP(F15,purchase!D:D,purchase!K:K,""))) | Q15: =IF(OR(L15="",M15=""),"",M15/L15) | R15: =IF(OR(P15="",Q15=""),"",Q15-P15)
A16: 12 | B16: =IF(OR(C16="",F16=""),"", "PRD-" & TEXT(DAY(C16),"00") & CHOOSE(MONTH(C16),"A","B","C","D","E","F","G","H","I","J","K","L") & TEXT(YEAR(C16),"00") & "-" & RIGHT(F16,4)) | D16: =IF(F16="","",_xlfn.XLOOKUP(F16,purchase!D:D,purchase!#REF!,"")) | E16: =IF(F16="","",_xlfn.XLOOKUP(F16,purchase!D:D,purchase!B:B,"")) | G16: =IF(H16="NRFC","Natural Rubber Field Coagulam","") | H16: =IF(F16="","",_xlfn.XLOOKUP(F16,purchase!D:D,purchase!#REF!,"")) | I16: =IF(J16="ISNR20","Natural Rubber-TSNR (ISNR-20)","") | J16: =IF(H16="NRFC","ISNR20","") | K16: =_xlfn.SINGLE(IF(F16="","",_xlfn.XLOOKUP(F16,purchase!D:D,purchase!#REF!,""))) | N16: =IF(F16="","", MAX(0, _xlfn.XLOOKUP(F16,purchase!D:D,purchase!#REF!,"") - SUMIFS(L:L,F:F,F16))) | O16: =IF(OR(L16="",M16=""),"",L16-M16) | P16: =_xlfn.SINGLE(IF(F16="","",_xlfn.XLOOKUP(F16,purchase!D:D,purchase!K:K,""))) | Q16: =IF(OR(L16="",M16=""),"",M16/L16) | R16: =IF(OR(P16="",Q16=""),"",Q16-P16)
... A2504: 2500 | B2504: =IF(OR(C2504="",F2504=""),"", "PRD-" & TEXT(DAY(C2504),"00") & CHOOSE(MONTH(C2504),"A","B","C","D","E","F","G","H","I","J","K","L") & TEXT(YEAR(C2504),"00") & "-" & RIGHT(F2504,4)) | D2504: =IF(F2504="","",_xlfn.XLOOKUP(F2504,purchase!D:D,purchase!#REF!,"")) | E2504: =IF(F2504="","",_xlfn.XLOOKUP(F2504,purchase!D:D,purchase!B:B,"")) | G2504: =IF(H2504="NRFC","Natural Rubber Field Coagulam","") | H2504: =IF(F2504="","",_xlfn.XLOOKUP(F2504,purchase!D:D,purchase!#REF!,"")) | I2504: =IF(J2504="ISNR20","Natural Rubber-TSNR (ISNR-20)","") | J2504: =IF(H2504="NRFC","ISNR20","") | K2504: =_xlfn.SINGLE(IF(F2504="","",_xlfn.XLOOKUP(F2504,purchase!D:D,purchase!#REF!,""))) | N2504: =IF(F2504="","", MAX(0, _xlfn.XLOOKUP(F2504,purchase!D:D,purchase!#REF!,"") - SUMIFS(L:L,F:F,F2504))) | O2504: =IF(OR(L2504="",M2504=""),"",L2504-M2504) | P2504: =_xlfn.SINGLE(IF(F2504="","",_xlfn.XLOOKUP(F2504,purchase!D:D,purchase!K:K,""))) | Q2504: =IF(OR(L2504="",M2504=""),"",M2504/L2504) | R2504: =IF(OR(P2504="",Q2504=""),"",Q2504-P2504)
