Workbook

Sheet pcon
A1: MASTER CONTRACT - PURCHASE
A3: Sl.no | B3: Vendor Name | C3: Vendor ID | D3: Item | F3: Period | L3: Base price (per kg) | M3: Quantity (kgs) | Q3: Contract Violation Logic | Y3: RENEWAL REFERENCE
D4: Name | E4: Code | F4: Start | G4: End | H4: Days Remaining | I4: Status | J4: Deliveries so far | K4: Date of Recent Delivery | M4: Agreed Qty | N4: Delivered Qty till Date | O4: Remaining Quantity | P4: % Completion | Q4: Breach | R4: Breach Responsibility | S4: Penalty / Discount (%) | T4: Revised Rate | U4: Penalty / Discount Value | V4: Remedy Days | W4: Remedy Deadline | X4: Remedy Status
A5: 1 | D5: =IF(E5="NRFC","Natural Rubber Field Coagulam","") | H5: =IF(G5="","",G5-TODAY()) | I5: =IF(G5="","", IF(G5<TODAY(), IF(O5>0,"Violated","Completed"), IF(H5<=7,"Expiring Soon", "Active"))) | J5: =IF(C5="","",COUNTIFS(purchase!$C:$C,$C5,purchase!$E:$E,$E5,purchase!$G:$G,">="&$F5,purchase!$G:$G,"<="&$G5)) | K5: =IF(COUNTIFS(purchase!$C:$C,$C5,purchase!$E:$E,$E5,purchase!$G:$G,">="&$F5,purchase!$G:$G,"<="&$G5)=0,"",_xlfn.MAXIFS(purchase!$G:$G,purchase!$C:$C,$C5,purchase!$E:$E,$E5,purchase!$G:$G,">="&$F5,purchase!$G:$G,"<="&$G5)) | N5: =IF(M5="","",SUMIFS(purchase!$N:$N,purchase!$C:$C,$C5,purchase!$E:$E,$E5,purchase!$G:$G,">="&$F5,purchase!$G:$G,"<="&$G5)) | O5: =IF(M5="","",M5-N5) | P5: =IF(M5=0,"",N5/M5) | Q5: =IF(OR(G5="",O5=""),"", IF(AND(G5<TODAY(),O5>0),"YES","NO")) | T5: =IF(Q5="YES", IF(R5="Company",L5*(1+S5),IF(R5="Vendor",L5*(1-S5),"")),"") | U5: =IF(Q5="YES",O5*T5,"") | W5: =IF(Q5="YES",G5+V5,"") | X5: =IF(Q5="YES",IF(TODAY()>W5,"OVERDUE","WITHIN TIME"),"")
A6: 2 | D6: =IF(E6="NRFC","Natural Rubber Field Coagulam","") | H6: =IF(G6="","",G6-TODAY()) | I6: =IF(G6="","", IF(G6<TODAY(), IF(O6>0,"Violated","Completed"), IF(H6<=7,"Expiring Soon", "Active"))) | J6: =IF(C6="","",COUNTIFS(purchase!$C:$C,$C6,purchase!$E:$E,$E6,purchase!$G:$G,">="&$F6,purchase!$G:$G,"<="&$G6)) | K6: =IF(COUNTIFS(purchase!$C:$C,$C6,purchase!$E:$E,$E6,purchase!$G:$G,">="&$F6,purchase!$G:$G,"<="&$G6)=0,"",_xlfn.MAXIFS(purchase!$G:$G,purchase!$C:$C,$C6,purchase!$E:$E,$E6,purchase!$G:$G,">="&$F6,purchase!$G:$G,"<="&$G6)) | N6: =IF(M6="","",SUMIFS(purchase!$N:$N,purchase!$C:$C,$C6,purchase!$E:$E,$E6,purchase!$G:$G,">="&$F6,purchase!$G:$G,"<="&$G6)) | O6: =IF(M6="","",M6-N6) | P6: =IF(M6=0,"",N6/M6) | Q6: =IF(OR(G6="",O6=""),"", IF(AND(G6<TODAY(),O6>0),"YES","NO")) | T6: =IF(Q6="YES", IF(R6="Company",L6*(1+S6),IF(R6="Vendor",L6*(1-S6),"")),"") | U6: =IF(Q6="YES",O6*T6,"") | W6: =IF(Q6="YES",G6+V6,"") | X6: =IF(Q6="YES",IF(TODAY()>W6,"OVERDUE","WITHIN TIME"),"")
A7: 3 | D7: =IF(E7="NRFC","Natural Rubber Field Coagulam","") | H7: =IF(G7="","",G7-TODAY()) | I7: =IF(G7="","", IF(G7<TODAY(), IF(O7>0,"Violated","Completed"), IF(H7<=7,"Expiring Soon", "Active"))) | J7: =IF(C7="","",COUNTIFS(purchase!$C:$C,$C7,purchase!$E:$E,$E7,purchase!$G:$G,">="&$F7,purchase!$G:$G,"<="&$G7)) | K7: =IF(COUNTIFS(purchase!$C:$C,$C7,purchase!$E:$E,$E7,purchase!$G:$G,">="&$F7,purchase!$G:$G,"<="&$G7)=0,"",_xlfn.MAXIFS(purchase!$G:$G,purchase!$C:$C,$C7,purchase!$E:$E,$E7,purchase!$G:$G,">="&$F7,purchase!$G:$G,"<="&$G7)) | N7: =IF(M7="","",SUMIFS(purchase!$N:$N,purchase!$C:$C,$C7,purchase!$E:$E,$E7,purchase!$G:$G,">="&$F7,purchase!$G:$G,"<="&$G7)) | O7: =IF(M7="","",M7-N7) | P7: =IF(M7=0,"",N7/M7) | Q7: =IF(OR(G7="",O7=""),"", IF(AND(G7<TODAY(),O7>0),"YES","NO")) | T7: =IF(Q7="YES", IF(R7="Company",L7*(1+S7),IF(R7="Vendor",L7*(1-S7),"")),"") | U7: =IF(Q7="YES",O7*T7,"") | W7: =IF(Q7="YES",G7+V7,"") | X7: =IF(Q7="YES",IF(TODAY()>W7,"OVERDUE","WITHIN TIME"),"")
A8: 4 | D8: =IF(E8="NRFC","Natural Rubber Field Coagulam","") | H8: =IF(G8="","",G8-TODAY()) | I8: =IF(G8="","", IF(G8<TODAY(), IF(O8>0,"Violated","Completed"), IF(H8<=7,"Expiring Soon", "Active"))) | J8: =IF(C8="","",COUNTIFS(purchase!$C:$C,$C8,purchase!$E:$E,$E8,purchase!$G:$G,">="&$F8,purchase!$G:$G,"<="&$G8)) | K8: =IF(COUNTIFS(purchase!$C:$C,$C8,purchase!$E:$E,$E8,purchase!$G:$G,">="&$F8,purchase!$G:$G,"<="&$G8)=0,"",_xlfn.MAXIFS(purchase!$G:$G,purchase!$C:$C,$C8,purchase!$E:$E,$E8,purchase!$G:$G,">="&$F8,purchase!$G:$G,"<="&$G8)) | N8: =IF(M8="","",SUMIFS(purchase!$N:$N,purchase!$C:$C,$C8,purchase!$E:$E,$E8,purchase!$G:$G,">="&$F8,purchase!$G:$G,"<="&$G8)) | O8: =IF(M8="","",M8-N8) | P8: =IF(M8=0,"",N8/M8) | Q8: =IF(OR(G8="",O8=""),"", IF(AND(G8<TODAY(),O8>0),"YES","NO")) | T8: =IF(Q8="YES", IF(R8="Company",L8*(1+S8),IF(R8="Vendor",L8*(1-S8),"")),"") | U8: =IF(Q8="YES",O8*T8,"") | W8: =IF(Q8="YES",G8+V8,"") | X8: =IF(Q8="YES",IF(TODAY()>W8,"OVERDUE","WITHIN TIME"),"")
A9: 5 | D9: =IF(E9="NRFC","Natural Rubber Field Coagulam","") | H9: =IF(G9="","",G9-TODAY()) | I9: =IF(G9="","", IF(G9<TODAY(), IF(O9>0,"Violated","Completed"), IF(H9<=7,"Expiring Soon", "Active"))) | J9: =IF(C9="","",COUNTIFS(purchase!$C:$C,$C9,purchase!$E:$E,$E9,purchase!$G:$G,">="&$F9,purchase!$G:$G,"<="&$G9)) | K9: =IF(COUNTIFS(purchase!$C:$C,$C9,purchase!$E:$E,$E9,purchase!$G:$G,">="&$F9,purchase!$G:$G,"<="&$G9)=0,"",_xlfn.MAXIFS(purchase!$G:$G,purchase!$C:$C,$C9,purchase!$E:$E,$E9,purchase!$G:$G,">="&$F9,purchase!$G:$G,"<="&$G9)) | N9: =IF(M9="","",SUMIFS(purchase!$N:$N,purchase!$C:$C,$C9,purchase!$E:$E,$E9,purchase!$G:$G,">="&$F9,purchase!$G:$G,"<="&$G9)) | O9: =IF(M9="","",M9-N9) | P9: =IF(M9=0,"",N9/M9) | Q9: =IF(OR(G9="",O9=""),"", IF(AND(G9<TODAY(),O9>0),"YES","NO")) | T9: =IF(Q9="YES", IF(R9="Company",L9*(1+S9),IF(R9="Vendor",L9*(1-S9),"")),"") | U9: =IF(Q9="YES",O9*T9,"") | W9: =IF(Q9="YES",G9+V9,"") | X9: =IF(Q9="YES",IF(TODAY()>W9,"OVERDUE","WITHIN TIME"),"")
A10: 6 | D10: =IF(E10="NRFC","Natural Rubber Field Coagulam","") | H10: =IF(G10="","",G10-TODAY()) | I10: =IF(G10="","", IF(G10<TODAY(), IF(O10>0,"Violated","Completed"), IF(H10<=7,"Expiring Soon", "Active"))) | J10: =IF(C10="","",COUNTIFS(purchase!$C:$C,$C10,purchase!$E:$E,$E10,purchase!$G:$G,">="&$F10,purchase!$G:$G,"<="&$G10)) | K10: =IF(COUNTIFS(purchase!$C:$C,$C10,purchase!$E:$E,$E10,purchase!$G:$G,">="&$F10,purchase!$G:$G,"<="&$G10)=0,"",_xlfn.MAXIFS(purchase!$G:$G,purchase!$C:$C,$C10,purchase!$E:$E,$E10,purchase!$G:$G,">="&$F10,purchase!$G:$G,"<="&$G10)) | N10: =IF(M10="","",SUMIFS(purchase!$N:$N,purchase!$C:$C,$C10,purchase!$E:$E,$E10,purchase!$G:$G,">="&$F10,purchase!$G:$G,"<="&$G10)) | O10: =IF(M10="","",M10-N10) | P10: =IF(M10=0,"",N10/M10) | Q10: =IF(OR(G10="",O10=""),"", IF(AND(G10<TODAY(),O10>0),"YES","NO")) | T10: =IF(Q10="YES", IF(R10="Company",L10*(1+S10),IF(R10="Vendor",L10*(1-S10),"")),"") | U10: =IF(Q10="YES",O10*T10,"") | W10: =IF(Q10="YES",G10+V10,"") | X10: =IF(Q10="YES",IF(TODAY()>W10,"OVERDUE","WITHIN TIME"),"")
A11: 7 | D11: =IF(E11="NRFC","Natural Rubber Field Coagulam","") | H11: =IF(G11="","",G11-TODAY()) | I11: =IF(G11="","", IF(G11<TODAY(), IF(O11>0,"Violated","Completed"), IF(H11<=7,"Expiring Soon", "Active"))) | J11: =IF(C11="","",COUNTIFS(purchase!$C:$C,$C11,purchase!$E:$E,$E11,purchase!$G:$G,">="&$F11,purchase!$G:$G,"<="&$G11)) | K11: =IF(COUNTIFS(purchase!$C:$C,$C11,purchase!$E:$E,$E11,purchase!$G:$G,">="&$F11,purchase!$G:$G,"<="&$G11)=0,"",_xlfn.MAXIFS(purchase!$G:$G,purchase!$C:$C,$C11,purchase!$E:$E,$E11,purchase!$G:$G,">="&$F11,purchase!$G:$G,"<="&$G11)) | N11: =IF(M11="","",SUMIFS(purchase!$N:$N,purchase!$C:$C,$C11,purchase!$E:$E,$E11,purchase!$G:$G,">="&$F11,purchase!$G:$G,"<="&$G11)) | O11: =IF(M11="","",M11-N11) | P11: =IF(M11=0,"",N11/M11) | Q11: =IF(OR(G11="",O11=""),"", IF(AND(G11<TODAY(),O11>0),"YES","NO")) | T11: =IF(Q11="YES", IF(R11="Company",L11*(1+S11),IF(R11="Vendor",L11*(1-S11),"")),"") | U11: =IF(Q11="YES",O11*T11,"") | W11: =IF(Q11="YES",G11+V11,"") | X11: =IF(Q11="YES",IF(TODAY()>W11,"OVERDUE","WITHIN TIME"),"")
A12: 8 | D12: =IF(E12="NRFC","Natural Rubber Field Coagulam","") | H12: =IF(G12="","",G12-TODAY()) | I12: =IF(G12="","", IF(G12<TODAY(), IF(O12>0,"Violated","Completed"), IF(H12<=7,"Expiring Soon", "Active"))) | J12: =IF(C12="","",COUNTIFS(purchase!$C:$C,$C12,purchase!$E:$E,$E12,purchase!$G:$G,">="&$F12,purchase!$G:$G,"<="&$G12)) | K12: =IF(COUNTIFS(purchase!$C:$C,$C12,purchase!$E:$E,$E12,purchase!$G:$G,">="&$F12,purchase!$G:$G,"<="&$G12)=0,"",_xlfn.MAXIFS(purchase!$G:$G,purchase!$C:$C,$C12,purchase!$E:$E,$E12,purchase!$G:$G,">="&$F12,purchase!$G:$G,"<="&$G12)) | N12: =IF(M12="","",SUMIFS(purchase!$N:$N,purchase!$C:$C,$C12,purchase!$E:$E,$E12,purchase!$G:$G,">="&$F12,purchase!$G:$G,"<="&$G12)) | O12: =IF(M12="","",M12-N12) | P12: =IF(M12=0,"",N12/M12) | Q12: =IF(OR(G12="",O12=""),"", IF(AND(G12<TODAY(),O12>0),"YES","NO")) | T12: =IF(Q12="YES", IF(R12="Company",L12*(1+S12),IF(R12="Vendor",L12*(1-S12),"")),"") | U12: =IF(Q12="YES",O12*T12,"") | W12: =IF(Q12="YES",G12+V12,"") | X12: =IF(Q12="YES",IF(TODAY()>W12,"OVERDUE","WITHIN TIME"),"")
A13: 9 | D13: =IF(E13="NRFC","Natural Rubber Field Coagulam","") | H13: =IF(G13="","",G13-TODAY()) | I13: =IF(G13="","", IF(G13<TODAY(), IF(O13>0,"Violated","Completed"), IF(H13<=7,"Expiring Soon", "Active"))) | J13: =IF(C13="","",COUNTIFS(purchase!$C:$C,$C13,purchase!$E:$E,$E13,purchase!$G:$G,">="&$F13,purchase!$G:$G,"<="&$G13)) | K13: =IF(COUNTIFS(purchase!$C:$C,$C13,purchase!$E:$E,$E13,purchase!$G:$G,">="&$F13,purchase!$G:$G,"<="&$G13)=0,"",_xlfn.MAXIFS(purchase!$G:$G,purchase!$C:$C,$C13,purchase!$E:$E,$E13,purchase!$G:$G,">="&$F13,purchase!$G:$G,"<="&$G13)) | N13: =IF(M13="","",SUMIFS(purchase!$N:$N,purchase!$C:$C,$C13,purchase!$E:$E,$E13,purchase!$G:$G,">="&$F13,purchase!$G:$G,"<="&$G13)) | O13: =IF(M13="","",M13-N13) | P13: =IF(M13=0,"",N13/M13) | Q13: =IF(OR(G13="",O13=""),"", IF(AND(G13<TODAY(),O13>0),"YES","NO")) | T13: =IF(Q13="YES", IF(R13="Company",L13*(1+S13),IF(R13="Vendor",L13*(1-S13),"")),"") | U13: =IF(Q13="YES",O13*T13,"") | W13: =IF(Q13="YES",G13+V13,"") | X13: =IF(Q13="YES",IF(TODAY()>W13,"OVERDUE","WITHIN TIME"),"")
A14: 10 | D14: =IF(E14="NRFC","Natural Rubber Field Coagulam","") | H14: =IF(G14="","",G14-TODAY()) | I14: =IF(G14="","", IF(G14<TODAY(), IF(O14>0,"Violated","Completed"), IF(H14<=7,"Expiring Soon", "Active"))) | J14: =IF(C14="","",COUNTIFS(purchase!$C:$C,$C14,purchase!$E:$E,$E14,purchase!$G:$G,">="&$F14,purchase!$G:$G,"<="&$G14)) | K14: =IF(COUNTIFS(purchase!$C:$C,$C14,purchase!$E:$E,$E14,purchase!$G:$G,">="&$F14,purchase!$G:$G,"<="&$G14)=0,"",_xlfn.MAXIFS(purchase!$G:$G,purchase!$C:$C,$C14,purchase!$E:$E,$E14,purchase!$G:$G,">="&$F14,purchase!$G:$G,"<="&$G14)) | N14: =IF(M14="","",SUMIFS(purchase!$N:$N,purchase!$C:$C,$C14,purchase!$E:$E,$E14,purchase!$G:$G,">="&$F14,purchase!$G:$G,"<="&$G14)) | O14: =IF(M14="","",M14-N14) | P14: =IF(M14=0,"",N14/M14) | Q14: =IF(OR(G14="",O14=""),"", IF(AND(G14<TODAY(),O14>0),"YES","NO")) | T14: =IF(Q14="YES", IF(R14="Company",L14*(1+S14),IF(R14="Vendor",L14*(1-S14),"")),"") | U14: =IF(Q14="YES",O14*T14,"") | W14: =IF(Q14="YES",G14+V14,"") | X14: =IF(Q14="YES",IF(TODAY()>W14,"OVERDUE","WITHIN TIME"),"")
A15: 11 | D15: =IF(E15="NRFC","Natural Rubber Field Coagulam","") | H15: =IF(G15="","",G15-TODAY()) | I15: =IF(G15="","", IF(G15<TODAY(), IF(O15>0,"Violated","Completed"), IF(H15<=7,"Expiring Soon", "Active"))) | J15: =IF(C15="","",COUNTIFS(purchase!$C:$C,$C15,purchase!$E:$E,$E15,purchase!$G:$G,">="&$F15,purchase!$G:$G,"<="&$G15)) | K15: =IF(COUNTIFS(purchase!$C:$C,$C15,purchase!$E:$E,$E15,purchase!$G:$G,">="&$F15,purchase!$G:$G,"<="&$G15)=0,"",_xlfn.MAXIFS(purchase!$G:$G,purchase!$C:$C,$C15,purchase!$E:$E,$E15,purchase!$G:$G,">="&$F15,purchase!$G:$G,"<="&$G15)) | N15: =IF(M15="","",SUMIFS(purchase!$N:$N,purchase!$C:$C,$C15,purchase!$E:$E,$E15,purchase!$G:$G,">="&$F15,purchase!$G:$G,"<="&$G15)) | O15: =IF(M15="","",M15-N15) | P15: =IF(M15=0,"",N15/M15) | Q15: =IF(OR(G15="",O15=""),"", IF(AND(G15<TODAY(),O15>0),"YES","NO")) | T15: =IF(Q15="YES", IF(R15="Company",L15*(1+S15),IF(R15="Vendor",L15*(1-S15),"")),"") | U15: =IF(Q15="YES",O15*T15,"") | W15: =IF(Q15="YES",G15+V15,"") | X15: =IF(Q15="YES",IF(TODAY()>W15,"OVERDUE","WITHIN TIME"),"")
A16: 12 | D16: =IF(E16="NRFC","Natural Rubber Field Coagulam","") | H16: =IF(G16="","",G16-TODAY()) | I16: =IF(G16="","", IF(G16<TODAY(), IF(O16>0,"Violated","Completed"), IF(H16<=7,"Expiring Soon", "Active"))) | J16: =IF(C16="","",COUNTIFS(purchase!$C:$C,$C16,purchase!$E:$E,$E16,purchase!$G:$G,">="&$F16,purchase!$G:$G,"<="&$G16)) | K16: =IF(COUNTIFS(purchase!$C:$C,$C16,purchase!$E:$E,$E16,purchase!$G:$G,">="&$F16,purchase!$G:$G,"<="&$G16)=0,"",_xlfn.MAXIFS(purchase!$G:$G,purchase!$C:$C,$C16,purchase!$E:$E,$E16,purchase!$G:$G,">="&$F16,purchase!$G:$G,"<="&$G16)) | N16: =IF(M16="","",SUMIFS(purchase!$N:$N,purchase!$C:$C,$C16,purchase!$E:$E,$E16,purchase!$G:$G,">="&$F16,purchase!$G:$G,"<="&$G16)) | O16: =IF(M16="","",M16-N16) | P16: =IF(M16=0,"",N16/M16) | Q16: =IF(OR(G16="",O16=""),"", IF(AND(G16<TODAY(),O16>0),"YES","NO")) | T16: =IF(Q16="YES", IF(R16="Company",L16*(1+S16),IF(R16="Vendor",L16*(1-S16),"")),"") | U16: =IF(Q16="YES",O16*T16,"") | W16: =IF(Q16="YES",G16+V16,"") | X16: =IF(Q16="YES",IF(TODAY()>W16,"OVERDUE","WITHIN TIME"),"")
... A2004: 2000 | D2004: =IF(E2004="NRFC","Natural Rubber Field Coagulam","") | H2004: =IF(G2004="","",G2004-TODAY()) | I2004: =IF(G2004="","", IF(G2004<TODAY(), IF(O2004>0,"Violated","Completed"), IF(H2004<=7,"Expiring Soon", "Active"))) | J2004: =IF(C2004="","",COUNTIFS(purchase!$C:$C,$C2004,purchase!$E:$E,$E2004,purchase!$G:$G,">="&$F2004,purchase!$G:$G,"<="&$G2004)) | K2004: =IF(COUNTIFS(purchase!$C:$C,$C2004,purchase!$E:$E,$E2004,purchase!$G:$G,">="&$F2004,purchase!$G:$G,"<="&$G2004)=0,"",_xlfn.MAXIFS(purchase!$G:$G,purchase!$C:$C,$C2004,purchase!$E:$E,$E2004,purchase!$G:$G,">="&$F2004,purchase!$G:$G,"<="&$G2004)) | N2004: =IF(M2004="","",SUMIFS(purchase!$N:$N,purchase!$C:$C,$C2004,purchase!$E:$E,$E2004,purchase!$G:$G,">="&$F2004,purchase!$G:$G,"<="&$G2004)) | O2004: =IF(M2004="","",M2004-N2004) | P2004: =IF(M2004=0,"",N2004/M2004) | Q2004: =IF(OR(G2004="",O2004=""),"", IF(AND(G2004<TODAY(),O2004>0),"YES","NO")) | T2004: =IF(Q2004="YES", IF(R2004="Company",L2004*(1+S2004),IF(R2004="Vendor",L2004*(1-S2004),"")),"") | U2004: =IF(Q2004="YES",O2004*T2004,"") | W2004: =IF(Q2004="YES",G2004+V2004,"") | X2004: =IF(Q2004="YES",IF(TODAY()>W2004,"OVERDUE","WITHIN TIME"),"")

Sheet scon
A1: MASTER CONTRACT - SALES
A3: Sl.no | B3: Customer Name | C3: Customer ID | D3: Item | F3: Period | L3: Base price (per kg) | M3: Quantity (kgs) | Q3: Contract Violation Logic | Y3: RENEWAL REFERENCE
D4: Name | E4: Code | F4: Start | G4: End | H4: Days Remaining | I4: Status | J4: Sales so far | K4: Date of Recent Sale | M4: Agreed Qty | N4: Sold Qty till Date | O4: Remaining Quantity | P4: % Completion | Q4: Breach | R4: Breach Responsibility | S4: Penalty / Discount (%) | T4: Revised Rate | U4: Penalty / Discount Value | V4: Remedy Days | W4: Remedy Deadline | X4: Remedy Status
A5: 1 | B5: Ganga Govind | C5: 77584 | D5: Natural Rubber Field Coagulum | E5: NRFC | F5: 46165 | G5: 46302 | H5: =IF(G5="","",G5-TODAY()) | I5: =IF(C5="","",COUNTIFS(sales!$C:$C,$C5,sales!$E:$E,$E5,sales!$H:$H,">="&$F5,sales!$H:$H,"<="&$G5)) | J5: =IF(C5="","", COUNTIFS( sales!$C:$C,$C5, sales!$E:$E,$E5, sales!$H:$H,">="&$F5, sales!$H:$H,"<="& $G5)) | K5: =IF(COUNTIFS(sales!C:C, C5)=0,"", _xlfn.MAXIFS(sales!H:H, sales!C:C, C5)) | L5: 143 | M5: 123000 | N5: =IF(C5="","",SUMIFS(sales!$I:$I,sales!$C:$C,$C5,sales!$E:$E,$E5,sales!$H:$H,">="&$F5,sales!$H:$H,"<="&$G5)) | O5: =IF(M5="","",M5-N5) | P5: =IFERROR((N5/M5)*100,0) | Q5: =IF(OR(G5="",O5=""),"",IF(AND(G5<TODAY(),O5>0),"YES","NO")) | R5: Pending | S5: 0.1 | T5: =IF(Q5="YES", IF(R5="Company",L5*(1+S5),IF(R5="Vendor",L5*(1-S5),"")),"") | U5: =IF(Q5="YES",O5*T5,"") | V5: 31 | W5: =IF(AND(Q5="YES",V5<>""),G5+V5,"") | X5: =IF(Q5<>"YES","",IF(O5<=0,"CLEARED",IF(TODAY()<=W5,"IN REMEDY","OVERDUE")))
A6: 2 | D6: =IF(E6="ISNR20","Natural Rubber-TSNR (ISNR-20)","") | H6: =IF(G6="","",G6-TODAY()) | I6: =IF(G6="","", IF(G6<TODAY(), IF(O6>0,"Violated","Completed"), IF(H6<=7,"Expiring Soon", "Active"))) | J6: =IF(C6="","", COUNTIFS( sales!$C:$C,$C6, sales!$E:$E,$E6, sales!$H:$H,">="&$F6, sales!$H:$H,"<="&$G6 )) | K6: =IF(COUNTIFS(sales!C:C, C6)=0,"", _xlfn.MAXIFS(sales!H:H, sales!C:C, C6)) | N6: =IF(C6="","", SUMIFS( sales!$I:$I, sales!$C:$C,$C6, sales!$E:$E,$E6, sales!$H:$H,">="&$F6, sales!$H:$H,"<="&$G6 )) | O6: =IF(M6="","",M6-N6) | P6: =IF(M6=0,"",N6/M6) | Q6: =IF(OR(G6="",O6=""),"", IF(AND(G6<TODAY(),O6>0),"YES","NO")) | T6: =IF(Q6="YES", IF(R6="Company",L6*(1+S6),IF(R6="Vendor",L6*(1-S6),"")),"") | U6: =IF(Q6="YES",O6*T6,"") | W6: =IF(Q6="YES",G6+V6,"") | X6: =IF(Q6="YES",IF(TODAY()>W6,"OVERDUE","WITHIN TIME"),"")
A7: 3 | D7: =IF(E7="ISNR20","Natural Rubber-TSNR (ISNR-20)","") | H7: =IF(G7="","",G7-TODAY()) | I7: =IF(G7="","", IF(G7<TODAY(), IF(O7>0,"Violated","Completed"), IF(H7<=7,"Expiring Soon", "Active"))) | J7: =IF(C7="","", COUNTIFS( sales!$C:$C,$C7, sales!$E:$E,$E7, sales!$H:$H,">="&$F7, sales!$H:$H,"<="&$G7 )) | K7: =IF(COUNTIFS(sales!C:C, C7)=0,"", _xlfn.MAXIFS(sales!H:H, sales!C:C, C7)) | N7: =IF(C7="","", SUMIFS( sales!$I:$I, sales!$C:$C,$C7, sales!$E:$E,$E7, sales!$H:$H,">="&$F7, sales!$H:$H,"<="&$G7 )) | O7: =IF(M7="","",M7-N7) | P7: =IF(M7=0,"",N7/M7) | Q7: =IF(OR(G7="",O7=""),"", IF(AND(G7<TODAY(),O7>0),"YES","NO")) | T7: =IF(Q7="YES", IF(R7="Company",L7*(1+S7),IF(R7="Vendor",L7*(1-S7),"")),"") | U7: =IF(Q7="YES",O7*T7,"") | W7: =IF(Q7="YES",G7+V7,"") | X7: =IF(Q7="YES",IF(TODAY()>W7,"OVERDUE","WITHIN TIME"),"")
A8: 4 | D8: =IF(E8="ISNR20","Natural Rubber-TSNR (ISNR-20)","") | H8: =IF(G8="","",G8-TODAY()) | I8: =IF(G8="","", IF(G8<TODAY(), IF(O8>0,"Violated","Completed"), IF(H8<=7,"Expiring Soon", "Active"))) | J8: =IF(C8="","", COUNTIFS( sales!$C:$C,$C8, sales!$E:$E,$E8, sales!$H:$H,">="&$F8, sales!$H:$H,"<="&$G8 )) | K8: =IF(COUNTIFS(sales!C:C, C8)=0,"", _xlfn.MAXIFS(sales!H:H, sales!C:C, C8)) | N8: =IF(C8="","", SUMIFS( sales!$I:$I, sales!$C:$C,$C8, sales!$E:$E,$E8, sales!$H:$H,">="&$F8, sales!$H:$H,"<="&$G8 )) | O8: =IF(M8="","",M8-N8) | P8: =IF(M8=0,"",N8/M8) | Q8: =IF(OR(G8="",O8=""),"", IF(AND(G8<TODAY(),O8>0),"YES","NO")) | T8: =IF(Q8="YES", IF(R8="Company",L8*(1+S8),IF(R8="Vendor",L8*(1-S8),"")),"") | U8: =IF(Q8="YES",O8*T8,"") | W8: =IF(Q8="YES",G8+V8,"") | X8: =IF(Q8="YES",IF(TODAY()>W8,"OVERDUE","WITHIN TIME"),"")
A9: 5 | D9: =IF(E9="ISNR20","Natural Rubber-TSNR (ISNR-20)","") | H9: =IF(G9="","",G9-TODAY()) | I9: =IF(G9="","", IF(G9<TODAY(), IF(O9>0,"Violated","Completed"), IF(H9<=7,"Expiring Soon", "Active"))) | J9: =IF(C9="","", COUNTIFS( sales!$C:$C,$C9, sales!$E:$E,$E9, sales!$H:$H,">="&$F9, sales!$H:$H,"<="&$G9 )) | K9: =IF(COUNTIFS(sales!C:C, C9)=0,"", _xlfn.MAXIFS(sales!H:H, sales!C:C, C9)) | N9: =IF(C9="","", SUMIFS( sales!$I:$I, sales!$C:$C,$C9, sales!$E:$E,$E9, sales!$H:$H,">="&$F9, sales!$H:$H,"<="&$G9 )) | O9: =IF(M9="","",M9-N9) | P9: =IF(M9=0,"",N9/M9) | Q9: =IF(OR(G9="",O9=""),"", IF(AND(G9<TODAY(),O9>0),"YES","NO")) | T9: =IF(Q9="YES", IF(R9="Company",L9*(1+S9),IF(R9="Vendor",L9*(1-S9),"")),"") | U9: =IF(Q9="YES",O9*T9,"") | W9: =IF(Q9="YES",G9+V9,"") | X9: =IF(Q9="YES",IF(TODAY()>W9,"OVERDUE","WITHIN TIME"),"")
A10: 6 | D10: =IF(E10="ISNR20","Natural Rubber-TSNR (ISNR-20)","") | H10: =IF(G10="","",G10-TODAY()) | I10: =IF(G10="","", IF(G10<TODAY(), IF(O10>0,"Violated","Completed"), IF(H10<=7,"Expiring Soon", "Active"))) | J10: =IF(C10="","", COUNTIFS( sales!$C:$C,$C10, sales!$E:$E,$E10, sales!$H:$H,">="&$F10, sales!$H:$H,"<="&$G10 )) | K10: =IF(COUNTIFS(sales!C:C, C10)=0,"", _xlfn.MAXIFS(sales!H:H, sales!C:C, C10)) | N10: =IF(C10="","", SUMIFS( sales!$I:$I, sales!$C:$C,$C10, sales!$E:$E,$E10, sales!$H:$H,">="&$F10, sales!$H:$H,"<="&$G10 )) | O10: =IF(M10="","",M10-N10) | P10: =IF(M10=0,"",N10/M10) | Q10: =IF(OR(G10="",O10=""),"", IF(AND(G10<TODAY(),O10>0),"YES","NO")) | T10: =IF(Q10="YES", IF(R10="Company",L10*(1+S10),IF(R10="Vendor",L10*(1-S10),"")),"") | U10: =IF(Q10="YES",O10*T10,"") | W10: =IF(Q10="YES",G10+V10,"") | X10: =IF(Q10="YES",IF(TODAY()>W10,"OVERDUE","WITHIN TIME"),"")
A11: 7 | D11: =IF(E11="ISNR20","Natural Rubber-TSNR (ISNR-20)","") | H11: =IF(G11="","",G11-TODAY()) | I11: =IF(G11="","", IF(G11<TODAY(), IF(O11>0,"Violated","Completed"), IF(H11<=7,"Expiring Soon", "Active"))) | J11: =IF(C11="","", COUNTIFS( sales!$C:$C,$C11, sales!$E:$E,$E11, sales!$H:$H,">="&$F11, sales!$H:$H,"<="&$G11 )) | K11: =IF(COUNTIFS(sales!C:C, C11)=0,"", _xlfn.MAXIFS(sales!H:H, sales!C:C, C11)) | N11: =IF(C11="","", SUMIFS( sales!$I:$I, sales!$C:$C,$C11, sales!$E:$E,$E11, sales!$H:$H,">="&$F11, sales!$H:$H,"<="&$G11 )) | O11: =IF(M11="","",M11-N11) | P11: =IF(M11=0,"",N11/M11) | Q11: =IF(OR(G11="",O11=""),"", IF(AND(G11<TODAY(),O11>0),"YES","NO")) | T11: =IF(Q11="YES", IF(R11="Company",L11*(1+S11),IF(R11="Vendor",L11*(1-S11),"")),"") | U11: =IF(Q11="YES",O11*T11,"") | W11: =IF(Q11="YES",G11+V11,"") | X11: =IF(Q11="YES",IF(TODAY()>W11,"OVERDUE","WITHIN TIME"),"")
A12: 8 | D12: =IF(E12="ISNR20","Natural Rubber-TSNR (ISNR-20)","") | H12: =IF(G12="","",G12-TODAY()) | I12: =IF(G12="","", IF(G12<TODAY(), IF(O12>0,"Violated","Completed"), IF(H12<=7,"Expiring Soon", "Active"))) | J12: =IF(C12="","", COUNTIFS( sales!$C:$C,$C12, sales!$E:$E,$E12, sales!$H:$H,">="&$F12, sales!$H:$H,"<="&$G12 )) | K12: =IF(COUNTIFS(sales!C:C, C12)=0,"", _xlfn.MAXIFS(sales!H:H, sales!C:C, C12)) | N12: =IF(C12="","", SUMIFS( sales!$I:$I, sales!$C:$C,$C12, sales!$E:$E,$E12, sales!$H:$H,">="&$F12, sales!$H:$H,"<="&$G12 )) | O12: =IF(M12="","",M12-N12) | P12: =IF(M12=0,"",N12/M12) | Q12: =IF(OR(G12="",O12=""),"", IF(AND(G12<TODAY(),O12>0),"YES","NO")) | T12: =IF(Q12="YES", IF(R12="Company",L12*(1+S12),IF(R12="Vendor",L12*(1-S12),"")),"") | U12: =IF(Q12="YES",O12*T12,"") | W12: =IF(Q12="YES",G12+V12,"") | X12: =IF(Q12="YES",IF(TODAY()>W12,"OVERDUE","WITHIN TIME"),"")
A13: 9 | D13: =IF(E13="ISNR20","Natural Rubber-TSNR (ISNR-20)","") | H13: =IF(G13="","",G13-TODAY()) | I13: =IF(G13="","", IF(G13<TODAY(), IF(O13>0,"Violated","Completed"), IF(H13<=7,"Expiring Soon", "Active"))) | J13: =IF(C13="","", COUNTIFS( sales!$C:$C,$C13, sales!$E:$E,$E13, sales!$H:$H,">="&$F13, sales!$H:$H,"<="&$G13 )) | K13: =IF(COUNTIFS(sales!C:C, C13)=0,"", _xlfn.MAXIFS(sales!H:H, sales!C:C, C13)) | N13: =IF(C13="","", SUMIFS( sales!$I:$I, sales!$C:$C,$C13, sales!$E:$E,$E13, sales!$H:$H,">="&$F13, sales!$H:$H,"<="&$G13 )) | O13: =IF(M13="","",M13-N13) | P13: =IF(M13=0,"",N13/M13) | Q13: =IF(OR(G13="",O13=""),"", IF(AND(G13<TODAY(),O13>0),"YES","NO")) | T13: =IF(Q13="YES", IF(R13="Company",L13*(1+S13),IF(R13="Vendor",L13*(1-S13),"")),"") | U13: =IF(Q13="YES",O13*T13,"") | W13: =IF(Q13="YES",G13+V13,"") | X13: =IF(Q13="YES",IF(TODAY()>W13,"OVERDUE","WITHIN TIME"),"")
A14: 10 | D14: =IF(E14="ISNR20","Natural Rubber-TSNR (ISNR-20)","") | H14: =IF(G14="","",G14-TODAY()) | I14: =IF(G14="","", IF(G14<TODAY(), IF(O14>0,"Violated","Completed"), IF(H14<=7,"Expiring Soon", "Active"))) | J14: =IF(C14="","", COUNTIFS( sales!$C:$C,$C14, sales!$E:$E,$E14, sales!$H:$H,">="&$F14, sales!$H:$H,"<="&$G14 )) | K14: =IF(COUNTIFS(sales!C:C, C14)=0,"", _xlfn.MAXIFS(sales!H:H, sales!C:C, C14)) | N14: =IF(C14="","", SUMIFS( sales!$I:$I, sales!$C:$C,$C14, sales!$E:$E,$E14, sales!$H:$H,">="&$F14, sales!$H:$H,"<="&$G14 )) | O14: =IF(M14="","",M14-N14) | P14: =IF(M14=0,"",N14/M14) | Q14: =IF(OR(G14="",O14=""),"", IF(AND(G14<TODAY(),O14>0),"YES","NO")) | T14: =IF(Q14="YES", IF(R14="Company",L14*(1+S14),IF(R14="Vendor",L14*(1-S14),"")),"") | U14: =IF(Q14="YES",O14*T14,"") | W14: =IF(Q14="YES",G14+V14,"") | X14: =IF(Q14="YES",IF(TODAY()>W14,"OVERDUE","WITHIN TIME"),"")
A15: 11 | D15: =IF(E15="ISNR20","Natural Rubber-TSNR (ISNR-20)","") | H15: =IF(G15="","",G15-TODAY()) | I15: =IF(G15="","", IF(G15<TODAY(), IF(O15>0,"Violated","Completed"), IF(H15<=7,"Expiring Soon", "Active"))) | J15: =IF(C15="","", COUNTIFS( sales!$C:$C,$C15, sales!$E:$E,$E15, sales!$H:$H,">="&$F15, sales!$H:$H,"<="&$G15 )) | K15: =IF(COUNTIFS(sales!C:C, C15)=0,"", _xlfn.MAXIFS(sales!H:H, sales!C:C, C15)) | N15: =IF(C15="","", SUMIFS( sales!$I:$I, sales!$C:$C,$C15, sales!$E:$E,$E15, sales!$H:$H,">="&$F15, sales!$H:$H,"<="&$G15 )) | O15: =IF(M15="","",M15-N15) | P15: =IF(M15=0,"",N15/M15) | Q15: =IF(OR(G15="",O15=""),"", IF(AND(G15<TODAY(),O15>0),"YES","NO")) | T15: =IF(Q15="YES", IF(R15="Company",L15*(1+S15),IF(R15="Vendor",L15*(1-S15),"")),"") | U15: =IF(Q15="YES",O15*T15,"") | W15: =IF(Q15="YES",G15+V15,"") | X15: =IF(Q15="YES",IF(TODAY()>W15,"OVERDUE","WITHIN TIME"),"")
A16: 12 | D16: =IF(E16="ISNR20","Natural Rubber-TSNR (ISNR-20)","") | H16: =IF(G16="","",G16-TODAY()) | I16: =IF(G16="","", IF(G16<TODAY(), IF(O16>0,"Violated","Completed"), IF(H16<=7,"Expiring Soon", "Active"))) | J16: =IF(C16="","", COUNTIFS( sales!$C:$C,$C16, sales!$E:$E,$E16, sales!$H:$H,">="&$F16, sales!$H:$H,"<="&$G16 )) | K16: =IF(COUNTIFS(sales!C:C, C16)=0,"", _xlfn.MAXIFS(sales!H:H, sales!C:C, C16)) | N16: =IF(C16="","", SUMIFS( sales!$I:$I, sales!$C:$C,$C16, sales!$E:$E,$E16, sales!$H:$H,">="&$F16, sales!$H:$H,"<="&$G16 )) | O16: =IF(M16="","",M16-N16) | P16: =IF(M16=0,"",N16/M16) | Q16: =IF(OR(G16="",O16=""),"", IF(AND(G16<TODAY(),O16>0),"YES","NO")) | T16: =IF(Q16="YES", IF(R16="Company",L16*(1+S16),IF(R16="Vendor",L16*(1-S16),"")),"") | U16: =IF(Q16="YES",O16*T16,"") | W16: =IF(Q16="YES",G16+V16,"") | X16: =IF(Q16="YES",IF(TODAY()>W16,"OVERDUE","WITHIN TIME"),"")
A17: 13 | D17: =IF(E17="ISNR20","Natural Rubber-TSNR (ISNR-20)","") | H17: =IF(G17="","",G17-TODAY()) | I17: =IF(G17="","", IF(G17<TODAY(), IF(O17>0,"Violated","Completed"), IF(H17<=7,"Expiring Soon", "Active"))) | J17: =IF(C17="","", COUNTIFS( sales!$C:$C,$C17, sales!$E:$E,$E17, sales!$H:$H,">="&$F17, sales!$H:$H,"<="&$G17 )) | K17: =IF(COUNTIFS(sales!C:C, C17)=0,"", _xlfn.MAXIFS(sales!H:H, sales!C:C, C17)) | N17: =IF(C17="","", SUMIFS( sales!$I:$I, sales!$C:$C,$C17, sales!$E:$E,$E17, sales!$H:$H,">="&$F17, sales!$H:$H,"<="&$G17 )) | O17: =IF(M17="","",M17-N17) | P17: =IF(M17=0,"",N17/M17) | Q17: =IF(OR(G17="",O17=""),"", IF(AND(G17<TODAY(),O17>0),"YES","NO")) | T17: =IF(Q17="YES", IF(R17="Company",L17*(1+S17),IF(R17="Vendor",L17*(1-S17),"")),"") | U17: =IF(Q17="YES",O17*T17,"") | W17: =IF(Q17="YES",G17+V17,"") | X17: =IF(Q17="YES",IF(TODAY()>W17,"OVERDUE","WITHIN TIME"),"")
... A2004: 2000 | D2004: =IF(E2004="ISNR20","Natural Rubber-TSNR (ISNR-20)","") | H2004: =IF(G2004="","",G2004-TODAY()) | I2004: =IF(G2004="","", IF(G2004<TODAY(), IF(O2004>0,"Violated","Completed"), IF(H2004<=7,"Expiring Soon", "Active"))) | J2004: =IF(C2004="","", COUNTIFS( sales!$C:$C,$C2004, sales!$E:$E,$E2004, sales!$H:$H,">="&$F2004, sales!$H:$H,"<="&$G2004 )) | K2004: =IF(COUNTIFS(sales!C:C, C2004)=0,"", _xlfn.MAXIFS(sales!H:H, sales!C:C, C2004)) | N2004: =IF(C2004="","", SUMIFS( sales!$I:$I, sales!$C:$C,$C2004, sales!$E:$E,$E2004, sales!$H:$H,">="&$F2004, sales!$H:$H,"<="&$G2004 )) | O2004: =IF(M2004="","",M2004-N2004) | P2004: =IF(M2004=0,"",N2004/M2004) | Q2004: =IF(OR(G2004="",O2004=""),"", IF(AND(G2004<TODAY(),O2004>0),"YES","NO")) | T2004: =IF(Q2004="YES", IF(R2004="Company",L2004*(1+S2004),IF(R2004="Vendor",L2004*(1-S2004),"")),"") | U2004: =IF(Q2004="YES",O2004*T2004,"") | W2004: =IF(Q2004="YES",G2004+V2004,"") | X2004: =IF(Q2004="YES",IF(TODAY()>W2004,"OVERDUE","WITHIN TIME"),"")

Sheet purchase
A1: PURCHASE SHEET
A3: Sl no. | B3: Vendor Name | C3: Vendor ID | D3: Item | F3: Invoice Number | G3: Date | I3: Weight (kgs) | Q3: Rates | U3: Amount (Rupees)
D4: Name | E4: Code | G4: Purchase Order | H4: Delivery | I4: Invoice Weight | J4: Before Unloading | K4: Carrier weight | L4: Received Weight | M4: No: of Bags (1kg per bag) | N4: NET Weight | O4: Calculated DRC (%) | P4: DRC Weight | Q4: Base Rate | R4: Adjusted Rate | S4: GST (%) | T4: TDS 194Q (%) | U4: Taxable Amount | V4: Unloading Charge | W4: GST Amount | X4: Gross Amount | Y4: TDS Amount | Z4: Net Payable
A5: 1 | B5: =_xlfn.XLOOKUP(C5,purchase!C:C,pcon!B:B,"") | D5: =_xlfn.XLOOKUP(C5,purchase!C:C,pcon!D:D,"") | E5: =_xlfn.XLOOKUP(C5,purchase!C:C,pcon!E:E,"") | L5: =IF(J5="","",J5-K5) | N5: =IF(L5="","",L5-M5) | P5: =IF(O5="","",N5 * O5) | Q5: =_xlfn.XLOOKUP(C5,pcon!C:C,pcon!L:L,"") | R5: =(Q5 / 80) * (O5 * 100) | U5: =IF(N5="","",R5 * N5) | W5: =IF(S5&U5="","",U5 * S5) | X5: =IF(W5="","",U5 + W5) | Y5: =IF(T5="","",U5 * T5) | Z5: =IF(U5="","",X5-V5-Y5)
A6: 2 | B6: =_xlfn.XLOOKUP(C6,purchase!C:C,pcon!B:B,"") | D6: =_xlfn.XLOOKUP(C6,purchase!C:C,pcon!D:D,"") | E6: =_xlfn.XLOOKUP(C6,purchase!C:C,pcon!E:E,"") | L6: =IF(J6="","",J6-K6) | N6: =IF(L6="","",L6-M6) | P6: =IF(O6="","",N6 * O6) | Q6: =_xlfn.XLOOKUP(C6,pcon!C:C,pcon!L:L,"") | R6: =(Q6 / 80) * (O6 * 100) | U6: =IF(N6="","",R6 * N6) | W6: =IF(S6&U6="","",U6 * S6) | X6: =IF(W6="","",U6 + W6) | Y6: =IF(T6="","",U6 * T6) | Z6: =IF(U6="","",X6-V6-Y6)
A7: 3 | B7: =_xlfn.XLOOKUP(C7,purchase!C:C,pcon!B:B,"") | D7: =_xlfn.XLOOKUP(C7,purchase!C:C,pcon!D:D,"") | E7: =_xlfn.XLOOKUP(C7,purchase!C:C,pcon!E:E,"") | L7: =IF(J7="","",J7-K7) | N7: =IF(L7="","",L7-M7) | P7: =IF(O7="","",N7 * O7) | Q7: =_xlfn.XLOOKUP(C7,pcon!C:C,pcon!L:L,"") | R7: =(Q7 / 80) * (O7 * 100) | U7: =IF(N7="","",R7 * N7) | W7: =IF(S7&U7="","",U7 * S7) | X7: =IF(W7="","",U7 + W7) | Y7: =IF(T7="","",U7 * T7) | Z7: =IF(U7="","",X7-V7-Y7)
A8: 4 | B8: =_xlfn.XLOOKUP(C8,purchase!C:C,pcon!B:B,"") | D8: =_xlfn.XLOOKUP(C8,purchase!C:C,pcon!D:D,"") | E8: =_xlfn.XLOOKUP(C8,purchase!C:C,pcon!E:E,"") | L8: =IF(J8="","",J8-K8) | N8: =IF(L8="","",L8-M8) | P8: =IF(O8="","",N8 * O8) | Q8: =_xlfn.XLOOKUP(C8,pcon!C:C,pcon!L:L,"") | R8: =(Q8 / 80) * (O8 * 100) | U8: =IF(N8="","",R8 * N8) | W8: =IF(S8&U8="","",U8 * S8) | X8: =IF(W8="","",U8 + W8) | Y8: =IF(T8="","",U8 * T8) | Z8: =IF(U8="","",X8-V8-Y8)
A9: 5 | B9: =_xlfn.XLOOKUP(C9,purchase!C:C,pcon!B:B,"") | D9: =_xlfn.XLOOKUP(C9,purchase!C:C,pcon!D:D,"") | E9: =_xlfn.XLOOKUP(C9,purchase!C:C,pcon!E:E,"") | L9: =IF(J9="","",J9-K9) | N9: =IF(L9="","",L9-M9) | P9: =IF(O9="","",N9 * O9) | Q9: =_xlfn.XLOOKUP(C9,pcon!C:C,pcon!L:L,"") | R9: =(Q9 / 80) * (O9 * 100) | U9: =IF(N9="","",R9 * N9) | W9: =IF(S9&U9="","",U9 * S9) | X9: =IF(W9="","",U9 + W9) | Y9: =IF(T9="","",U9 * T9) | Z9: =IF(U9="","",X9-V9-Y9)
A10: 6 | B10: =_xlfn.XLOOKUP(C10,purchase!C:C,pcon!B:B,"") | D10: =_xlfn.XLOOKUP(C10,purchase!C:C,pcon!D:D,"") | E10: =_xlfn.XLOOKUP(C10,purchase!C:C,pcon!E:E,"") | L10: =IF(J10="","",J10-K10) | N10: =IF(L10="","",L10-M10) | P10: =IF(O10="","",N10 * O10) | Q10: =_xlfn.XLOOKUP(C10,pcon!C:C,pcon!L:L,"") | R10: =(Q10 / 80) * (O10 * 100) | U10: =IF(N10="","",R10 * N10) | W10: =IF(S10&U10="","",U10 * S10) | X10: =IF(W10="","",U10 + W10) | Y10: =IF(T10="","",U10 * T10) | Z10: =IF(U10="","",X10-V10-Y10)
A11: 7 | B11: =_xlfn.XLOOKUP(C11,purchase!C:C,pcon!B:B,"") | D11: =_xlfn.XLOOKUP(C11,purchase!C:C,pcon!D:D,"") | E11: =_xlfn.XLOOKUP(C11,purchase!C:C,pcon!E:E,"") | L11: =IF(J11="","",J11-K11) | N11: =IF(L11="","",L11-M11) | P11: =IF(O11="","",N11 * O11) | Q11: =_xlfn.XLOOKUP(C11,pcon!C:C,pcon!L:L,"") | R11: =(Q11 / 80) * (O11 * 100) | U11: =IF(N11="","",R11 * N11) | W11: =IF(S11&U11="","",U11 * S11) | X11: =IF(W11="","",U11 + W11) | Y11: =IF(T11="","",U11 * T11) | Z11: =IF(U11="","",X11-V11-Y11)
A12: 8 | B12: =_xlfn.XLOOKUP(C12,purchase!C:C,pcon!B:B,"") | D12: =_xlfn.XLOOKUP(C12,purchase!C:C,pcon!D:D,"") | E12: =_xlfn.XLOOKUP(C12,purchase!C:C,pcon!E:E,"") | L12: =IF(J12="","",J12-K12) | N12: =IF(L12="","",L12-M12) | P12: =IF(O12="","",N12 * O12) | Q12: =_xlfn.XLOOKUP(C12,pcon!C:C,pcon!L:L,"") | R12: =(Q12 / 80) * (O12 * 100) | U12: =IF(N12="","",R12 * N12) | W12: =IF(S12&U12="","",U12 * S12) | X12: =IF(W12="","",U12 + W12) | Y12: =IF(T12="","",U12 * T12) | Z12: =IF(U12="","",X12-V12-Y12)
A13: 9 | B13: =_xlfn.XLOOKUP(C13,purchase!C:C,pcon!B:B,"") | D13: =_xlfn.XLOOKUP(C13,purchase!C:C,pcon!D:D,"") | E13: =_xlfn.XLOOKUP(C13,purchase!C:C,pcon!E:E,"") | L13: =IF(J13="","",J13-K13) | N13: =IF(L13="","",L13-M13) | P13: =IF(O13="","",N13 * O13) | Q13: =_xlfn.XLOOKUP(C13,pcon!C:C,pcon!L:L,"") | R13: =(Q13 / 80) * (O13 * 100) | U13: =IF(N13="","",R13 * N13) | W13: =IF(S13&U13="","",U13 * S13) | X13: =IF(W13="","",U13 + W13) | Y13: =IF(T13="","",U13 * T13) | Z13: =IF(U13="","",X13-V13-Y13)
A14: 10 | B14: =_xlfn.XLOOKUP(C14,purchase!C:C,pcon!B:B,"") | D14: =_xlfn.XLOOKUP(C14,purchase!C:C,pcon!D:D,"") | E14: =_xlfn.XLOOKUP(C14,purchase!C:C,pcon!E:E,"") | L14: =IF(J14="","",J14-K14) | N14: =IF(L14="","",L14-M14) | P14: =IF(O14="","",N14 * O14) | Q14: =_xlfn.XLOOKUP(C14,pcon!C:C,pcon!L:L,"") | R14: =(Q14 / 80) * (O14 * 100) | U14: =IF(N14="","",R14 * N14) | W14: =IF(S14&U14="","",U14 * S14) | X14: =IF(W14="","",U14 + W14) | Y14: =IF(T14="","",U14 * T14) | Z14: =IF(U14="","",X14-V14-Y14)
A15: 11 | B15: =_xlfn.XLOOKUP(C15,purchase!C:C,pcon!B:B,"") | D15: =_xlfn.XLOOKUP(C15,purchase!C:C,pcon!D:D,"") | E15: =_xlfn.XLOOKUP(C15,purchase!C:C,pcon!E:E,"") | L15: =IF(J15="","",J15-K15) | N15: =IF(L15="","",L15-M15) | P15: =IF(O15="","",N15 * O15) | Q15: =_xlfn.XLOOKUP(C15,pcon!C:C,pcon!L:L,"") | R15: =(Q15 / 80) * (O15 * 100) | U15: =IF(N15="","",R15 * N15) | W15: =IF(S15&U15="","",U15 * S15) | X15: =IF(W15="","",U15 + W15) | Y15: =IF(T15="","",U15 * T15) | Z15: =IF(U15="","",X15-V15-Y15)
A16: 12 | B16: =_xlfn.XLOOKUP(C16,purchase!C:C,pcon!B:B,"") | D16: =_xlfn.XLOOKUP(C16,purchase!C:C,pcon!D:D,"") | E16: =_xlfn.XLOOKUP(C16,purchase!C:C,pcon!E:E,"") | L16: =IF(J16="","",J16-K16) | N16: =IF(L16="","",L16-M16) | P16: =IF(O16="","",N16 * O16) | Q16: =_xlfn.XLOOKUP(C16,pcon!C:C,pcon!L:L,"") | R16: =(Q16 / 80) * (O16 * 100) | U16: =IF(N16="","",R16 * N16) | W16: =IF(S16&U16="","",U16 * S16) | X16: =IF(W16="","",U16 + W16) | Y16: =IF(T16="","",U16 * T16) | Z16: =IF(U16="","",X16-V16-Y16)
... A2504: 2500 | B2504: =_xlfn.XLOOKUP(C2504,purchase!C:C,pcon!B:B,"") | D2504: =_xlfn.XLOOKUP(C2504,purchase!C:C,pcon!D:D,"") | E2504: =_xlfn.XLOOKUP(C2504,purchase!C:C,pcon!E:E,"") | L2504: =IF(J2504="","",J2504-K2504) | N2504: =IF(L2504="","",L2504-M2504) | P2504: =IF(O2504="","",N2504 * O2504) | Q2504: =_xlfn.XLOOKUP(C2504,pcon!C:C,pcon!L:L,"") | R2504: =(Q2504 / 80) * (O2504 * 100) | U2504: =IF(N2504="","",R2504 * N2504) | W2504: =IF(S2504&U2504="","",U2504 * S2504) | X2504: =IF(W2504="","",U2504 + W2504) | Y2504: =IF(T2504="","",U2504 * T2504) | Z2504: =IF(U2504="","",X2504-V2504-Y2504)

Sheet sales
A1: SALES SHEET
A3: Sl no. | B3: Customer Name | C3: Customer ID | D3: Item | F3: Invoice Number | G3: Date | I3: Weight | J3: Base Rate | K3: Rates (%) | M3: Amount (Rupees)
D4: Name | E4: Code | G4: Sales Order | H4: Dispatch | K4: GST | L4: TCS 194Q | M4: Taxable Amount | N4: GST Amount | O4: Total | P4: Loading Charge | Q4: TCS Amount | R4: Net Recievable
A5: 1 | B5: =_xlfn.XLOOKUP(C5,sales!C:C,scon!B:B,"") | D5: =_xlfn.XLOOKUP(C5,sales!C:C,scon!D:D,"") | E5: =_xlfn.XLOOKUP(C5,sales!C:C,scon!E:E,"") | J5: =_xlfn.XLOOKUP(C5,sales!C:C,scon!L:L,"") | M5: =IF(I5="","",J5*I5) | N5: =IF(K5="","",M5 * K5) | O5: =IF(K5="","",M5 + N5) | Q5: =IF(L5&K5="","",M5 * L5) | R5: =IF(M5="","",O5+P5+Q5)
A6: 2 | B6: =_xlfn.XLOOKUP(C6,sales!C:C,scon!B:B,"") | D6: =_xlfn.XLOOKUP(C6,sales!C:C,scon!D:D,"") | E6: =_xlfn.XLOOKUP(C6,sales!C:C,scon!E:E,"") | J6: =_xlfn.XLOOKUP(C6,sales!C:C,scon!L:L,"") | M6: =IF(I6="","",J6*I6) | N6: =IF(K6="","",M6 * K6) | O6: =IF(K6="","",M6 + N6) | Q6: =IF(L6&K6="","",M6 * L6) | R6: =IF(M6="","",O6-P6-Q6)
A7: 3 | B7: =_xlfn.XLOOKUP(C7,sales!C:C,scon!B:B,"") | D7: =_xlfn.XLOOKUP(C7,sales!C:C,scon!D:D,"") | E7: =_xlfn.XLOOKUP(C7,sales!C:C,scon!E:E,"") | J7: =_xlfn.XLOOKUP(C7,sales!C:C,scon!L:L,"") | M7: =IF(I7="","",J7*I7) | N7: =IF(K7="","",M7 * K7) | O7: =IF(K7="","",M7 + N7) | Q7: =IF(L7&K7="","",M7 * L7) | R7: =IF(M7="","",O7-P7-Q7)
A8: 4 | B8: =_xlfn.XLOOKUP(C8,sales!C:C,scon!B:B,"") | D8: =_xlfn.XLOOKUP(C8,sales!C:C,scon!D:D,"") | E8: =_xlfn.XLOOKUP(C8,sales!C:C,scon!E:E,"") | J8: =_xlfn.XLOOKUP(C8,sales!C:C,scon!L:L,"") | M8: =IF(I8="","",J8*I8) | N8: =IF(K8="","",M8 * K8) | O8: =IF(K8="","",M8 + N8) | Q8: =IF(L8&K8="","",M8 * L8) | R8: =IF(M8="","",O8-P8-Q8)
A9: 5 | B9: =_xlfn.XLOOKUP(C9,sales!C:C,scon!B:B,"") | D9: =_xlfn.XLOOKUP(C9,sales!C:C,scon!D:D,"") | E9: =_xlfn.XLOOKUP(C9,sales!C:C,scon!E:E,"") | J9: =_xlfn.XLOOKUP(C9,sales!C:C,scon!L:L,"") | M9: =IF(I9="","",J9*I9) | N9: =IF(K9="","",M9 * K9) | O9: =IF(K9="","",M9 + N9) | Q9: =IF(L9&K9="","",M9 * L9) | R9: =IF(M9="","",O9-P9-Q9)
A10: 6 | B10: =_xlfn.XLOOKUP(C10,sales!C:C,scon!B:B,"") | D10: =_xlfn.XLOOKUP(C10,sales!C:C,scon!D:D,"") | E10: =_xlfn.XLOOKUP(C10,sales!C:C,scon!E:E,"") | J10: =_xlfn.XLOOKUP(C10,sales!C:C,scon!L:L,"") | M10: =IF(I10="","",J10*I10) | N10: =IF(K10="","",M10 * K10) | O10: =IF(K10="","",M10 + N10) | Q10: =IF(L10&K10="","",M10 * L10) | R10: =IF(M10="","",O10-P10-Q10)
A11: 7 | B11: =_xlfn.XLOOKUP(C11,sales!C:C,scon!B:B,"") | D11: =_xlfn.XLOOKUP(C11,sales!C:C,scon!D:D,"") | E11: =_xlfn.XLOOKUP(C11,sales!C:C,scon!E:E,"") | J11: =_xlfn.XLOOKUP(C11,sales!C:C,scon!L:L,"") | M11: =IF(I11="","",J11*I11) | N11: =IF(K11="","",M11 * K11) | O11: =IF(K11="","",M11 + N11) | Q11: =IF(L11&K11="","",M11 * L11) | R11: =IF(M11="","",O11-P11-Q11)
A12: 8 | B12: =_xlfn.XLOOKUP(C12,sales!C:C,scon!B:B,"") | D12: =_xlfn.XLOOKUP(C12,sales!C:C,scon!D:D,"") | E12: =_xlfn.XLOOKUP(C12,sales!C:C,scon!E:E,"") | J12: =_xlfn.XLOOKUP(C12,sales!C:C,scon!L:L,"") | M12: =IF(I12="","",J12*I12) | N12: =IF(K12="","",M12 * K12) | O12: =IF(K12="","",M12 + N12) | Q12: =IF(L12&K12="","",M12 * L12) | R12: =IF(M12="","",O12-P12-Q12)
A13: 9 | B13: =_xlfn.XLOOKUP(C13,sales!C:C,scon!B:B,"") | D13: =_xlfn.XLOOKUP(C13,sales!C:C,scon!D:D,"") | E13: =_xlfn.XLOOKUP(C13,sales!C:C,scon!E:E,"") | J13: =_xlfn.XLOOKUP(C13,sales!C:C,scon!L:L,"") | M13: =IF(I13="","",J13*I13) | N13: =IF(K13="","",M13 * K13) | O13: =IF(K13="","",M13 + N13) | Q13: =IF(L13&K13="","",M13 * L13) | R13: =IF(M13="","",O13-P13-Q13)
A14: 10 | B14: =_xlfn.XLOOKUP(C14,sales!C:C,scon!B:B,"") | D14: =_xlfn.XLOOKUP(C14,sales!C:C,scon!D:D,"") | E14: =_xlfn.XLOOKUP(C14,sales!C:C,scon!E:E,"") | J14: =_xlfn.XLOOKUP(C14,sales!C:C,scon!L:L,"") | M14: =IF(I14="","",J14*I14) | N14: =IF(K14="","",M14 * K14) | O14: =IF(K14="","",M14 + N14) | Q14: =IF(L14&K14="","",M14 * L14) | R14: =IF(M14="","",O14-P14-Q14)
A15: 11 | B15: =_xlfn.XLOOKUP(C15,sales!C:C,scon!B:B,"") | D15: =_xlfn.XLOOKUP(C15,sales!C:C,scon!D:D,"") | E15: =_xlfn.XLOOKUP(C15,sales!C:C,scon!E:E,"") | J15: =_xlfn.XLOOKUP(C15,sales!C:C,scon!L:L,"") | M15: =IF(I15="","",J15*I15) | N15: =IF(K15="","",M15 * K15) | O15: =IF(K15="","",M15 + N15) | Q15: =IF(L15&K15="","",M15 * L15) | R15: =IF(M15="","",O15-P15-Q15)
A16: 12 | B16: =_xlfn.XLOOKUP(C16,sales!C:C,scon!B:B,"") | D16: =_xlfn.XLOOKUP(C16,sales!C:C,scon!D:D,"") | E16: =_xlfn.XLOOKUP(C16,sales!C:C,scon!E:E,"") | J16: =_xlfn.XLOOKUP(C16,sales!C:C,scon!L:L,"") | M16: =IF(I16="","",J16*I16) | N16: =IF(K16="","",M16 * K16) | O16: =IF(K16="","",M16 + N16) | Q16: =IF(L16&K16="","",M16 * L16) | R16: =IF(M16="","",O16-P16-Q16)
A17: 13 | B17: =_xlfn.XLOOKUP(C17,sales!C:C,scon!B:B,"") | D17: =_xlfn.XLOOKUP(C17,sales!C:C,scon!D:D,"") | E17: =_xlfn.XLOOKUP(C17,sales!C:C,scon!E:E,"") | J17: =_xlfn.XLOOKUP(C17,sales!C:C,scon!L:L,"") | M17: =IF(I17="","",J17*I17) | N17: =IF(K17="","",M17 * K17) | O17: =IF(K17="","",M17 + N17) | Q17: =IF(L17&K17="","",M17 * L17) | R17: =IF(M17="","",O17-P17-Q17)
... A2504: 2500 | B2504: =_xlfn.XLOOKUP(C2504,sales!C:C,scon!B:B,"") | D2504: =_xlfn.XLOOKUP(C2504,sales!C:C,scon!D:D,"") | E2504: =_xlfn.XLOOKUP(C2504,sales!C:C,scon!E:E,"") | J2504: =_xlfn.XLOOKUP(C2504,sales!C:C,scon!L:L,"") | M2504: =IF(I2504="","",J2504*I2504) | N2504: =IF(K2504="","",M2504 * K2504) | O2504: =IF(K2504="","",M2504 + N2504) | Q2504: =IF(L2504&K2504="","",M2504 * L2504) | R2504: =IF(M2504="","",O2504-P2504-Q2504)

Sheet production
A1: MASTER PRODUCTION SHEET
A3: Sl no. | B3: Batch ID | C3: Production Date | D3: Supplier Name | E3: Supplier ID | F3: Invoice Number | G3: Item | K3: Weight (kgs) | P3: DRC (%)
G4: Raw Material | H4: Code | I4: Product | J4: Code | K4: Quantity Available | L4: Input | M4: Output | N4: Remaining Quantity | O4: Production Loss | P4: Initial (Test) | Q4: Actual | R4: DRC Variance
A5: 1 | B5: =IF(OR(C5="",F5=""),"", "PRD-" & TEXT(DAY(C5),"00") & CHOOSE(MONTH(C5),"A","B","C","D","E","F","G","H","I","J","K","L") & TEXT(YEAR(C5),"00") & "-" & RIGHT(F5,4)) | D5: =IF(F5="","",_xlfn.XLOOKUP(F5,purchase!F:F,purchase!B:B,"")) | E5: =IF(F5="","",_xlfn.XLOOKUP(F5,purchase!F:F,purchase!C:C,"")) | G5: =IF(H5="NRFC","Natural Rubber Field Coagulam","") | H5: =IF(F5="","",_xlfn.XLOOKUP(F5,purchase!F:F,purchase!E:E,"")) | I5: =IF(J5="ISNR20","Natural Rubber-TSNR (ISNR-20)","") | J5: =IF(H5="NRFC","ISNR20","") | K5: =_xlfn.SINGLE(IF(F5="","",_xlfn.XLOOKUP(F5,purchase!F:F,purchase!N:N,""))) | N5: =IF(F5="","", MAX(0, _xlfn.XLOOKUP(F5,purchase!F:F,purchase!N:N,"") - SUMIFS(L:L,F:F,F5))) | O5: =IF(OR(L5="",M5=""),"",L5-M5) | P5: =_xlfn.SINGLE(IF(F5="","",_xlfn.XLOOKUP(F5,purchase!F:F,purchase!O:O,""))) | Q5: =IF(OR(L5="",M5=""),"",M5/L5) | R5: =IF(OR(P5="",Q5=""),"",Q5-P5)
A6: 2 | B6: =IF(OR(C6="",F6=""),"", "PRD-" & TEXT(DAY(C6),"00") & CHOOSE(MONTH(C6),"A","B","C","D","E","F","G","H","I","J","K","L") & TEXT(YEAR(C6),"00") & "-" & RIGHT(F6,4)) | D6: =IF(F6="","",_xlfn.XLOOKUP(F6,purchase!F:F,purchase!B:B,"")) | E6: =IF(F6="","",_xlfn.XLOOKUP(F6,purchase!F:F,purchase!C:C,"")) | G6: =IF(H6="NRFC","Natural Rubber Field Coagulam","") | H6: =IF(F6="","",_xlfn.XLOOKUP(F6,purchase!F:F,purchase!E:E,"")) | I6: =IF(J6="ISNR20","Natural Rubber-TSNR (ISNR-20)","") | J6: =IF(H6="NRFC","ISNR20","") | K6: =_xlfn.SINGLE(IF(F6="","",_xlfn.XLOOKUP(F6,purchase!F:F,purchase!N:N,""))) | N6: =IF(F6="","", MAX(0, _xlfn.XLOOKUP(F6,purchase!F:F,purchase!N:N,"") - SUMIFS(L:L,F:F,F6))) | O6: =IF(OR(L6="",M6=""),"",L6-M6) | P6: =_xlfn.SINGLE(IF(F6="","",_xlfn.XLOOKUP(F6,purchase!F:F,purchase!O:O,""))) | Q6: =IF(OR(L6="",M6=""),"",M6/L6) | R6: =IF(OR(P6="",Q6=""),"",Q6-P6)
A7: 3 | B7: =IF(OR(C7="",F7=""),"", "PRD-" & TEXT(DAY(C7),"00") & CHOOSE(MONTH(C7),"A","B","C","D","E","F","G","H","I","J","K","L") & TEXT(YEAR(C7),"00") & "-" & RIGHT(F7,4)) | D7: =IF(F7="","",_xlfn.XLOOKUP(F7,purchase!F:F,purchase!B:B,"")) | E7: =IF(F7="","",_xlfn.XLOOKUP(F7,purchase!F:F,purchase!C:C,"")) | G7: =IF(H7="NRFC","Natural Rubber Field Coagulam","") | H7: =IF(F7="","",_xlfn.XLOOKUP(F7,purchase!F:F,purchase!E:E,"")) | I7: =IF(J7="ISNR20","Natural Rubber-TSNR (ISNR-20)","") | J7: =IF(H7="NRFC","ISNR20","") | K7: =_xlfn.SINGLE(IF(F7="","",_xlfn.XLOOKUP(F7,purchase!F:F,purchase!N:N,""))) | N7: =IF(F7="","", MAX(0, _xlfn.XLOOKUP(F7,purchase!F:F,purchase!N:N,"") - SUMIFS(L:L,F:F,F7))) | O7: =IF(OR(L7="",M7=""),"",L7-M7) | P7: =_xlfn.SINGLE(IF(F7="","",_xlfn.XLOOKUP(F7,purchase!F:F,purchase!O:O,""))) | Q7: =IF(OR(L7="",M7=""),"",M7/L7) | R7: =IF(OR(P7="",Q7=""),"",Q7-P7)
A8: 4 | B8: =IF(OR(C8="",F8=""),"", "PRD-" & TEXT(DAY(C8),"00") & CHOOSE(MONTH(C8),"A","B","C","D","E","F","G","H","I","J","K","L") & TEXT(YEAR(C8),"00") & "-" & RIGHT(F8,4)) | D8: =IF(F8="","",_xlfn.XLOOKUP(F8,purchase!F:F,purchase!B:B,"")) | E8: =IF(F8="","",_xlfn.XLOOKUP(F8,purchase!F:F,purchase!C:C,"")) | G8: =IF(H8="NRFC","Natural Rubber Field Coagulam","") | H8: =IF(F8="","",_xlfn.XLOOKUP(F8,purchase!F:F,purchase!E:E,"")) | I8: =IF(J8="ISNR20","Natural Rubber-TSNR (ISNR-20)","") | J8: =IF(H8="NRFC","ISNR20","") | K8: =_xlfn.SINGLE(IF(F8="","",_xlfn.XLOOKUP(F8,purchase!F:F,purchase!N:N,""))) | N8: =IF(F8="","", MAX(0, _xlfn.XLOOKUP(F8,purchase!F:F,purchase!N:N,"") - SUMIFS(L:L,F:F,F8))) | O8: =IF(OR(L8="",M8=""),"",L8-M8) | P8: =_xlfn.SINGLE(IF(F8="","",_xlfn.XLOOKUP(F8,purchase!F:F,purchase!O:O,""))) | Q8: =IF(OR(L8="",M8=""),"",M8/L8) | R8: =IF(OR(P8="",Q8=""),"",Q8-P8)
A9: 5 | B9: =IF(OR(C9="",F9=""),"", "PRD-" & TEXT(DAY(C9),"00") & CHOOSE(MONTH(C9),"A","B","C","D","E","F","G","H","I","J","K","L") & TEXT(YEAR(C9),"00") & "-" & RIGHT(F9,4)) | D9: =IF(F9="","",_xlfn.XLOOKUP(F9,purchase!F:F,purchase!B:B,"")) | E9: =IF(F9="","",_xlfn.XLOOKUP(F9,purchase!F:F,purchase!C:C,"")) | G9: =IF(H9="NRFC","Natural Rubber Field Coagulam","") | H9: =IF(F9="","",_xlfn.XLOOKUP(F9,purchase!F:F,purchase!E:E,"")) | I9: =IF(J9="ISNR20","Natural Rubber-TSNR (ISNR-20)","") | J9: =IF(H9="NRFC","ISNR20","") | K9: =_xlfn.SINGLE(IF(F9="","",_xlfn.XLOOKUP(F9,purchase!F:F,purchase!N:N,""))) | N9: =IF(F9="","", MAX(0, _xlfn.XLOOKUP(F9,purchase!F:F,purchase!N:N,"") - SUMIFS(L:L,F:F,F9))) | O9: =IF(OR(L9="",M9=""),"",L9-M9) | P9: =_xlfn.SINGLE(IF(F9="","",_xlfn.XLOOKUP(F9,purchase!F:F,purchase!O:O,""))) | Q9: =IF(OR(L9="",M9=""),"",M9/L9) | R9: =IF(OR(P9="",Q9=""),"",Q9-P9)
A10: 6 | B10: =IF(OR(C10="",F10=""),"", "PRD-" & TEXT(DAY(C10),"00") & CHOOSE(MONTH(C10),"A","B","C","D","E","F","G","H","I","J","K","L") & TEXT(YEAR(C10),"00") & "-" & RIGHT(F10,4)) | D10: =IF(F10="","",_xlfn.XLOOKUP(F10,purchase!F:F,purchase!B:B,"")) | E10: =IF(F10="","",_xlfn.XLOOKUP(F10,purchase!F:F,purchase!C:C,"")) | G10: =IF(H10="NRFC","Natural Rubber Field Coagulam","") | H10: =IF(F10="","",_xlfn.XLOOKUP(F10,purchase!F:F,purchase!E:E,"")) | I10: =IF(J10="ISNR20","Natural Rubber-TSNR (ISNR-20)","") | J10: =IF(H10="NRFC","ISNR20","") | K10: =_xlfn.SINGLE(IF(F10="","",_xlfn.XLOOKUP(F10,purchase!F:F,purchase!N:N,""))) | N10: =IF(F10="","", MAX(0, _xlfn.XLOOKUP(F10,purchase!F:F,purchase!N:N,"") - SUMIFS(L:L,F:F,F10))) | O10: =IF(OR(L10="",M10=""),"",L10-M10) | P10: =_xlfn.SINGLE(IF(F10="","",_xlfn.XLOOKUP(F10,purchase!F:F,purchase!O:O,""))) | Q10: =IF(OR(L10="",M10=""),"",M10/L10) | R10: =IF(OR(P10="",Q10=""),"",Q10-P10)
A11: 7 | B11: =IF(OR(C11="",F11=""),"", "PRD-" & TEXT(DAY(C11),"00") & CHOOSE(MONTH(C11),"A","B","C","D","E","F","G","H","I","J","K","L") & TEXT(YEAR(C11),"00") & "-" & RIGHT(F11,4)) | D11: =IF(F11="","",_xlfn.XLOOKUP(F11,purchase!F:F,purchase!B:B,"")) | E11: =IF(F11="","",_xlfn.XLOOKUP(F11,purchase!F:F,purchase!C:C,"")) | G11: =IF(H11="NRFC","Natural Rubber Field Coagulam","") | H11: =IF(F11="","",_xlfn.XLOOKUP(F11,purchase!F:F,purchase!E:E,"")) | I11: =IF(J11="ISNR20","Natural Rubber-TSNR (ISNR-20)","") | J11: =IF(H11="NRFC","ISNR20","") | K11: =_xlfn.SINGLE(IF(F11="","",_xlfn.XLOOKUP(F11,purchase!F:F,purchase!N:N,""))) | N11: =IF(F11="","", MAX(0, _xlfn.XLOOKUP(F11,purchase!F:F,purchase!N:N,"") - SUMIFS(L:L,F:F,F11))) | O11: =IF(OR(L11="",M11=""),"",L11-M11) | P11: =_xlfn.SINGLE(IF(F11="","",_xlfn.XLOOKUP(F11,purchase!F:F,purchase!O:O,""))) | Q11: =IF(OR(L11="",M11=""),"",M11/L11) | R11: =IF(OR(P11="",Q11=""),"",Q11-P11)
A12: 8 | B12: =IF(OR(C12="",F12=""),"", "PRD-" & TEXT(DAY(C12),"00") & CHOOSE(MONTH(C12),"A","B","C","D","E","F","G","H","I","J","K","L") & TEXT(YEAR(C12),"00") & "-" & RIGHT(F12,4)) | D12: =IF(F12="","",_xlfn.XLOOKUP(F12,purchase!F:F,purchase!B:B,"")) | E12: =IF(F12="","",_xlfn.XLOOKUP(F12,purchase!F:F,purchase!C:C,"")) | G12: =IF(H12="NRFC","Natural Rubber Field Coagulam","") | H12: =IF(F12="","",_xlfn.XLOOKUP(F12,purchase!F:F,purchase!E:E,"")) | I12: =IF(J12="ISNR20","Natural Rubber-TSNR (ISNR-20)","") | J12: =IF(H12="NRFC","ISNR20","") | K12: =_xlfn.SINGLE(IF(F12="","",_xlfn.XLOOKUP(F12,purchase!F:F,purchase!N:N,""))) | N12: =IF(F12="","", MAX(0, _xlfn.XLOOKUP(F12,purchase!F:F,purchase!N:N,"") - SUMIFS(L:L,F:F,F12))) | O12: =IF(OR(L12="",M12=""),"",L12-M12) | P12: =_xlfn.SINGLE(IF(F12="","",_xlfn.XLOOKUP(F12,purchase!F:F,purchase!O:O,""))) | Q12: =IF(OR(L12="",M12=""),"",M12/L12) | R12: =IF(OR(P12="",Q12=""),"",Q12-P12)
A13: 9 | B13: =IF(OR(C13="",F13=""),"", "PRD-" & TEXT(DAY(C13),"00") & CHOOSE(MONTH(C13),"A","B","C","D","E","F","G","H","I","J","K","L") & TEXT(YEAR(C13),"00") & "-" & RIGHT(F13,4)) | D13: =IF(F13="","",_xlfn.XLOOKUP(F13,purchase!F:F,purchase!B:B,"")) | E13: =IF(F13="","",_xlfn.XLOOKUP(F13,purchase!F:F,purchase!C:C,"")) | G13: =IF(H13="NRFC","Natural Rubber Field Coagulam","") | H13: =IF(F13="","",_xlfn.XLOOKUP(F13,purchase!F:F,purchase!E:E,"")) | I13: =IF(J13="ISNR20","Natural Rubber-TSNR (ISNR-20)","") | J13: =IF(H13="NRFC","ISNR20","") | K13: =_xlfn.SINGLE(IF(F13="","",_xlfn.XLOOKUP(F13,purchase!F:F,purchase!N:N,""))) | N13: =IF(F13="","", MAX(0, _xlfn.XLOOKUP(F13,purchase!F:F,purchase!N:N,"") - SUMIFS(L:L,F:F,F13))) | O13: =IF(OR(L13="",M13=""),"",L13-M13) | P13: =_xlfn.SINGLE(IF(F13="","",_xlfn.XLOOKUP(F13,purchase!F:F,purchase!O:O,""))) | Q13: =IF(OR(L13="",M13=""),"",M13/L13) | R13: =IF(OR(P13="",Q13=""),"",Q13-P13)
A14: 10 | B14: =IF(OR(C14="",F14=""),"", "PRD-" & TEXT(DAY(C14),"00") & CHOOSE(MONTH(C14),"A","B","C","D","E","F","G","H","I","J","K","L") & TEXT(YEAR(C14),"00") & "-" & RIGHT(F14,4)) | D14: =IF(F14="","",_xlfn.XLOOKUP(F14,purchase!F:F,purchase!B:B,"")) | E14: =IF(F14="","",_xlfn.XLOOKUP(F14,purchase!F:F,purchase!C:C,"")) | G14: =IF(H14="NRFC","Natural Rubber Field Coagulam","") | H14: =IF(F14="","",_xlfn.XLOOKUP(F14,purchase!F:F,purchase!E:E,"")) | I14: =IF(J14="ISNR20","Natural Rubber-TSNR (ISNR-20)","") | J14: =IF(H14="NRFC","ISNR20","") | K14: =_xlfn.SINGLE(IF(F14="","",_xlfn.XLOOKUP(F14,purchase!F:F,purchase!N:N,""))) | N14: =IF(F14="","", MAX(0, _xlfn.XLOOKUP(F14,purchase!F:F,purchase!N:N,"") - SUMIFS(L:L,F:F,F14))) | O14: =IF(OR(L14="",M14=""),"",L14-M14) | P14: =_xlfn.SINGLE(IF(F14="","",_xlfn.XLOOKUP(F14,purchase!F:F,purchase!O:O,""))) | Q14: =IF(OR(L14="",M14=""),"",M14/L14) | R14: =IF(OR(P14="",Q14=""),"",Q14-P14)
A15: 11 | B15: =IF(OR(C15="",F15=""),"", "PRD-" & TEXT(DAY(C15),"00") & CHOOSE(MONTH(C15),"A","B","C","D","E","F","G","H","I","J","K","L") & TEXT(YEAR(C15),"00") & "-" & RIGHT(F15,4)) | D15: =IF(F15="","",_xlfn.XLOOKUP(F15,purchase!F:F,purchase!B:B,"")) | E15: =IF(F15="","",_xlfn.XLOOKUP(F15,purchase!F:F,purchase!C:C,"")) | G15: =IF(H15="NRFC","Natural Rubber Field Coagulam","") | H15: =IF(F15="","",_xlfn.XLOOKUP(F15,purchase!F:F,purchase!E:E,"")) | I15: =IF(J15="ISNR20","Natural Rubber-TSNR (ISNR-20)","") | J15: =IF(H15="NRFC","ISNR20","") | K15: =_xlfn.SINGLE(IF(F15="","",_xlfn.XLOOKUP(F15,purchase!F:F,purchase!N:N,""))) | N15: =IF(F15="","", MAX(0, _xlfn.XLOOKUP(F15,purchase!F:F,purchase!N:N,"") - SUMIFS(L:L,F:F,F15))) | O15: =IF(OR(L15="",M15=""),"",L15-M15) | P15: =_xlfn.SINGLE(IF(F15="","",_xlfn.XLOOKUP(F15,purchase!F:F,purchase!O:O,""))) | Q15: =IF(OR(L15="",M15=""),"",M15/L15) | R15: =IF(OR(P15="",Q15=""),"",Q15-P15)
A16: 12 | B16: =IF(OR(C16="",F16=""),"", "PRD-" & TEXT(DAY(C16),"00") & CHOOSE(MONTH(C16),"A","B","C","D","E","F","G","H","I","J","K","L") & TEXT(YEAR(C16),"00") & "-" & RIGHT(F16,4)) | D16: =IF(F16="","",_xlfn.XLOOKUP(F16,purchase!F:F,purchase!B:B,"")) | E16: =IF(F16="","",_xlfn.XLOOKUP(F16,purchase!F:F,purchase!C:C,"")) | G16: =IF(H16="NRFC","Natural Rubber Field Coagulam","") | H16: =IF(F16="","",_xlfn.XLOOKUP(F16,purchase!F:F,purchase!E:E,"")) | I16: =IF(J16="ISNR20","Natural Rubber-TSNR (ISNR-20)","") | J16: =IF(H16="NRFC","ISNR20","") | K16: =_xlfn.SINGLE(IF(F16="","",_xlfn.XLOOKUP(F16,purchase!F:F,purchase!N:N,""))) | N16: =IF(F16="","", MAX(0, _xlfn.XLOOKUP(F16,purchase!F:F,purchase!N:N,"") - SUMIFS(L:L,F:F,F16))) | O16: =IF(OR(L16="",M16=""),"",L16-M16) | P16: =_xlfn.SINGLE(IF(F16="","",_xlfn.XLOOKUP(F16,purchase!F:F,purchase!O:O,""))) | Q16: =IF(OR(L16="",M16=""),"",M16/L16) | R16: =IF(OR(P16="",Q16=""),"",Q16-P16)
... A2504: 2500 | B2504: =IF(OR(C2504="",F2504=""),"", "PRD-" & TEXT(DAY(C2504),"00") & CHOOSE(MONTH(C2504),"A","B","C","D","E","F","G","H","I","J","K","L") & TEXT(YEAR(C2504),"00") & "-" & RIGHT(F2504,4)) | D2504: =IF(F2504="","",_xlfn.XLOOKUP(F2504,purchase!F:F,purchase!B:B,"")) | E2504: =IF(F2504="","",_xlfn.XLOOKUP(F2504,purchase!F:F,purchase!C:C,"")) | G2504: =IF(H2504="NRFC","Natural Rubber Field Coagulam","") | H2504: =IF(F2504="","",_xlfn.XLOOKUP(F2504,purchase!F:F,purchase!E:E,"")) | I2504: =IF(J2504="ISNR20","Natural Rubber-TSNR (ISNR-20)","") | J2504: =IF(H2504="NRFC","ISNR20","") | K2504: =_xlfn.SINGLE(IF(F2504="","",_xlfn.XLOOKUP(F2504,purchase!F:F,purchase!N:N,""))) | N2504: =IF(F2504="","", MAX(0, _xlfn.XLOOKUP(F2504,purchase!F:F,purchase!N:N,"") - SUMIFS(L:L,F:F,F2504))) | O2504: =IF(OR(L2504="",M2504=""),"",L2504-M2504) | P2504: =_xlfn.SINGLE(IF(F2504="","",_xlfn.XLOOKUP(F2504,purchase!F:F,purchase!O:O,""))) | Q2504: =IF(OR(L2504="",M2504=""),"",M2504/L2504) | R2504: =IF(OR(P2504="",Q2504=""),"",Q2504-P2504)
